Workbook
Name AI: [1]datos!$B$14:$B$57
Name CtrlInt: [1]datos!$V$2:$V$7
Name Cumplimiento: [1]datos!$R$2:$R$7
Name DeptoAI: [1]datos!$G$2:$G$15
Name eef_af: datos!$Z$43:$Z$53
Name eef_br: datos!#REF!
Name Emp: [1]datos!$G$27:$G$34
Name ExistNorma: [1]datos!$T$2:$T$7
Name Impacto: [1]datos!$X$2:$X$7
Name Prioridad1: [1]datos!$P$11:$P$16
Name Proceso: [1]datos!$E$2:$E$6
Name resultado2: '[1](3)_Plan_de_Accion'!$AF$3:$AF$7
Name RiesgoAsoc: [1]datos!$P$2:$P$7
Name subdir1: '[1](3)_Plan_de_Accion'!$AI$3:$AI$6
Name TipoHallazgo: [1]datos!$G$19:$G$23

Sheet (1)_Base_de_Datos
A3: NO. OBS | B3: OBSERVACION / RECOMENDACIÓN | C3: GRADO DE RIESGO | D3: CLASIFICACIÓN DE PROCESO AUDITADO | E3: ÁREA AUDITADA | F3: AÑO DE REVISIÓN | G3: CVE | H3: PERÍODO DE REVISIÓN | I3: REVISION CON CIFRAS AL | J3: NOMBRE DE LA AUDITORIA | K3: NOMBRE DEL MONITOREO | L3: CONCEPTO DEL HALLAZGO | M3: DESCRIPCION DEL HALLAZGO | N3: IMPLICACIÓN | O3: FUNDAMENTO | P3: CONTROL | Q3: TIPO DE HALLAZGO | R3: EMPRESA | S3: DEPTO DE AUDITORÍA INTERNA | T3: AUDITOR RESPONSABLE | U3: Area del Auditor | V3: FECHA DE ELABORACIÓN | W3: NIP | X3: NOMBRE DEL RESPONSABLE AUDITADO | Y3: PUESTO DEL RESPONSABLE AUDITADO | Z3: AREA DEL RESPONSABLE AUDITADO | AA3: DIRECCION RESPONSABLE | AB3: COMPROMISO INICIAL | AC3: FECHA COMPROMISO INICIAL
A4: 01 | B4: Observación | C4: MEDIO | D4: Control | E4: Calificación de Cartera | F4: 2026 | H4: 31 de Mayo de 2026 | I4: 31 de Mayo de 2026 | J4: CALIFICACION DE CARTERA | L4: Inconsistencias en el cálculo de la Probabilidad de Incumplimiento y Severidad de la Pérdida. | M4: a) Como resultado de la validación del cálculo de la Probabilidad de Incumplimiento se detectó un caso GREENING RENOVABLES S.A. DE C.V., que se calificó en sector Servicios debiendo ser Construcción de acuerdo a la carátula de autorización de fecha 15 de septiembre de 2025. b) Diferencia en las reserva de acuerdo a lo siguiente: En 1 cliente inconsistencia en el cálculo de la EI expuesta, después de aplicar la garantía líquida, lo cual se detalla en el reporte regulatorio R04-C-0434 Severidad de la Pérdida, lo que ocasiona cálculo erróneo de la reserva, Impacto $379.83 pesos. | N4: Incumplimiento a la CUB Anexo 22 | O4: CUB Anexo 22, CUB Artículo 114. | P4: Deficiencia del diseño del control | Q4: Diseño del Control Limitado | R4: Banco BASE | S4: Auditoría de Crédito Empresarial | T4: Blanca Nelly Gutiérrez Garza | U4: =IFERROR(VLOOKUP(T4,datos!$W$3:$X$23,2,0),"") | V4: 25 de Septiembre de 2026 | W4: 3731 | X4: =IFERROR(VLOOKUP($W4,Plantilla!$B$3:$AE$2497,2,0),"") | Y4: =IFERROR(VLOOKUP($W4,Plantilla!$B$3:$AE$2497,4,0),"") | Z4: =IFERROR(VLOOKUP($W4,Plantilla!$B$3:$AE$2496,4,0),"") | AA4: =IFERROR(VLOOKUP($W4,Plantilla!$B$3:$AJ$2496,17,0),"") | AB4: =IFERROR(IF('(3)_Plan_de_Accion'!M14<>"",'(3)_Plan_de_Accion'!M14,""),"") | AC4: =IFERROR(IF('(3)_Plan_de_Accion'!Q14<>"",'(3)_Plan_de_Accion'!Q14,""),"")
A5: 02 | B5: Observación | C5: BAJO | D5: Control | E5: Calificación de Cartera | F5: =IFERROR(IF($J5<>"",F4,""),"") | G5: =IFERROR(IF($J5<>"",G4,""),"") | H5: =IFERROR(IF($J5<>"",H4,""),"") | I5: =IFERROR(IF($J5<>"",I4,""),"") | J5: =IFERROR(IF($B5<>"",J4,""),"") | L5: Calidad de la información del Reporte Regulatorio R04-C-438. | M5: Derivado de la validación de la calidad de la información en los reportes regulatorios, en el reporte R04-C-0438, se detectó error el campo 45 Cuentas y Documentos por Cobrar, de acuerdo al instructivo de llenado, si los estados financiero se encuentran vencidos, este campo deberá llenarse con -999, sin embargo se esta presentando en -99. (5 clientes) | N5: Incumplimiento a Regulación Externa | O5: CUB_BD_R04_C-0430-0439_Cred com Act 11feb26 Instructivo | P5: Deficiencia del diseño del control | Q5: Diseño del Control Limitado | R5: =IFERROR(IF($J5<>"",R4,""),"") | S5: =IFERROR(IF($J5<>"",S4,""),"") | T5: =IFERROR(IF($J5<>"",T4,""),"") | U5: =IFERROR(IF($J5<>"",U4,""),"") | V5: =IFERROR(IF($J5<>"",V4,""),"") | W5: 3731 | X5: =IFERROR(VLOOKUP($W5,Plantilla!$B$3:$AE$2497,2,0),"") | Y5: =IFERROR(VLOOKUP($W5,Plantilla!$B$3:$AE$2497,4,0),"") | Z5: =IFERROR(VLOOKUP($W5,Plantilla!$B$3:$AE$2496,4,0),"") | AA5: =IFERROR(VLOOKUP($W5,Plantilla!$B$3:$AJ$2496,17,0),"") | AB5: =IFERROR(IF('(3)_Plan_de_Accion'!M23<>"",'(3)_Plan_de_Accion'!M23,""),"") | AC5: =IFERROR(IF('(3)_Plan_de_Accion'!Q23<>"",'(3)_Plan_de_Accion'!Q23,""),"")
A6: 03 | F6: =IFERROR(IF($J6<>"",F5,""),"") | G6: =IFERROR(IF($J6<>"",G5,""),"") | H6: =IFERROR(IF($J6<>"",H5,""),"") | I6: =IFERROR(IF($J6<>"",I5,""),"") | J6: =IFERROR(IF($B6<>"",J5,""),"") | R6: =IFERROR(IF($J6<>"",R5,""),"") | S6: =IFERROR(IF($J6<>"",S5,""),"") | T6: =IFERROR(IF($J6<>"",T5,""),"") | U6: =IFERROR(IF($J6<>"",U5,""),"") | V6: =IFERROR(IF($J6<>"",V5,""),"") | X6: =IFERROR(VLOOKUP($W6,Plantilla!$B$3:$AE$2497,2,0),"") | Y6: =IFERROR(VLOOKUP($W6,Plantilla!$B$3:$AE$2497,4,0),"") | Z6: =IFERROR(VLOOKUP($W6,Plantilla!$B$3:$AE$2496,4,0),"") | AA6: =IFERROR(VLOOKUP($W6,Plantilla!$B$3:$AJ$2496,17,0),"") | AB6: =IFERROR(IF('(3)_Plan_de_Accion'!M32<>"",'(3)_Plan_de_Accion'!M32,""),"") | AC6: =IFERROR(IF('(3)_Plan_de_Accion'!Q32<>"",'(3)_Plan_de_Accion'!Q32,""),"")
A7: 04 | F7: =IFERROR(IF($J7<>"",F6,""),"") | G7: =IFERROR(IF($J7<>"",G6,""),"") | H7: =IFERROR(IF($J7<>"",H6,""),"") | I7: =IFERROR(IF($J7<>"",I6,""),"") | J7: =IFERROR(IF($B7<>"",J6,""),"") | R7: =IFERROR(IF($J7<>"",R6,""),"") | S7: =IFERROR(IF($J7<>"",S6,""),"") | T7: =IFERROR(IF($J7<>"",T6,""),"") | U7: =IFERROR(IF($J7<>"",U6,""),"") | V7: =IFERROR(IF($J7<>"",V6,""),"") | X7: =IFERROR(VLOOKUP($W7,Plantilla!$B$3:$AE$2497,2,0),"") | Y7: =IFERROR(VLOOKUP($W7,Plantilla!$B$3:$AE$2497,4,0),"") | Z7: =IFERROR(VLOOKUP($W7,Plantilla!$B$3:$AE$2496,4,0),"") | AA7: =IFERROR(VLOOKUP($W7,Plantilla!$B$3:$AJ$2496,17,0),"") | AB7: =IFERROR(IF('(3)_Plan_de_Accion'!M41<>"",'(3)_Plan_de_Accion'!M41,""),"") | AC7: =IFERROR(IF('(3)_Plan_de_Accion'!Q41<>"",'(3)_Plan_de_Accion'!Q41,""),"")
A8: 05 | F8: =IFERROR(IF($J8<>"",F7,""),"") | G8: =IFERROR(IF($J8<>"",G7,""),"") | H8: =IFERROR(IF($J8<>"",H7,""),"") | I8: =IFERROR(IF($J8<>"",I7,""),"") | J8: =IFERROR(IF($B8<>"",J7,""),"") | R8: =IFERROR(IF($J8<>"",R7,""),"") | S8: =IFERROR(IF($J8<>"",S7,""),"") | T8: =IFERROR(IF($J8<>"",T7,""),"") | U8: =IFERROR(IF($J8<>"",U7,""),"") | V8: =IFERROR(IF($J8<>"",V7,""),"") | X8: =IFERROR(VLOOKUP($W8,Plantilla!$B$3:$AE$2497,2,0),"") | Y8: =IFERROR(VLOOKUP($W8,Plantilla!$B$3:$AE$2497,4,0),"") | Z8: =IFERROR(VLOOKUP($W8,Plantilla!$B$3:$AE$2496,4,0),"") | AA8: =IFERROR(VLOOKUP($W8,Plantilla!$B$3:$AJ$2496,17,0),"") | AB8: =IFERROR(IF('(3)_Plan_de_Accion'!M50<>"",'(3)_Plan_de_Accion'!M50,""),"") | AC8: =IFERROR(IF('(3)_Plan_de_Accion'!Q50<>"",'(3)_Plan_de_Accion'!Q50,""),"")
A9: 06 | F9: =IFERROR(IF($J9<>"",F8,""),"") | G9: =IFERROR(IF($J9<>"",G8,""),"") | H9: =IFERROR(IF($J9<>"",H8,""),"") | I9: =IFERROR(IF($J9<>"",I8,""),"") | J9: =IFERROR(IF($B9<>"",J8,""),"") | R9: =IFERROR(IF($J9<>"",R8,""),"") | S9: =IFERROR(IF($J9<>"",S8,""),"") | T9: =IFERROR(IF($J9<>"",T8,""),"") | U9: =IFERROR(IF($J9<>"",U8,""),"") | V9: =IFERROR(IF($J9<>"",V8,""),"") | X9: =IFERROR(VLOOKUP($W9,Plantilla!$B$3:$AE$2497,2,0),"") | Y9: =IFERROR(VLOOKUP($W9,Plantilla!$B$3:$AE$2497,4,0),"") | Z9: =IFERROR(VLOOKUP($W9,Plantilla!$B$3:$AE$2496,4,0),"") | AA9: =IFERROR(VLOOKUP($W9,Plantilla!$B$3:$AJ$2496,17,0),"") | AB9: =IFERROR(IF('(3)_Plan_de_Accion'!M59<>"",'(3)_Plan_de_Accion'!M59,""),"") | AC9: =IFERROR(IF('(3)_Plan_de_Accion'!Q59<>"",'(3)_Plan_de_Accion'!Q59,""),"")
A10: 07 | F10: =IFERROR(IF($J10<>"",F9,""),"") | G10: =IFERROR(IF($J10<>"",G9,""),"") | H10: =IFERROR(IF($J10<>"",H9,""),"") | I10: =IFERROR(IF($J10<>"",I9,""),"") | J10: =IFERROR(IF($B10<>"",J9,""),"") | R10: =IFERROR(IF($J10<>"",R9,""),"") | S10: =IFERROR(IF($J10<>"",S9,""),"") | T10: =IFERROR(IF($J10<>"",T9,""),"") | U10: =IFERROR(IF($J10<>"",U9,""),"") | V10: =IFERROR(IF($J10<>"",V9,""),"") | X10: =IFERROR(VLOOKUP($W10,Plantilla!$B$3:$AE$2497,2,0),"") | Y10: =IFERROR(VLOOKUP($W10,Plantilla!$B$3:$AE$2497,4,0),"") | Z10: =IFERROR(VLOOKUP($W10,Plantilla!$B$3:$AE$2496,4,0),"") | AA10: =IFERROR(VLOOKUP($W10,Plantilla!$B$3:$AJ$2496,17,0),"") | AB10: =IFERROR(IF('(3)_Plan_de_Accion'!M68<>"",'(3)_Plan_de_Accion'!M68,""),"") | AC10: =IFERROR(IF('(3)_Plan_de_Accion'!Q68<>"",'(3)_Plan_de_Accion'!Q68,""),"")
A11: 08 | F11: =IFERROR(IF($J11<>"",F10,""),"") | G11: =IFERROR(IF($J11<>"",G10,""),"") | H11: =IFERROR(IF($J11<>"",H10,""),"") | I11: =IFERROR(IF($J11<>"",I10,""),"") | J11: =IFERROR(IF($B11<>"",J10,""),"") | R11: =IFERROR(IF($J11<>"",R10,""),"") | S11: =IFERROR(IF($J11<>"",S10,""),"") | T11: =IFERROR(IF($J11<>"",T10,""),"") | U11: =IFERROR(IF($J11<>"",U10,""),"") | V11: =IFERROR(IF($J11<>"",V10,""),"") | X11: =IFERROR(VLOOKUP($W11,Plantilla!$B$3:$AE$2497,2,0),"") | Y11: =IFERROR(VLOOKUP($W11,Plantilla!$B$3:$AE$2497,4,0),"") | Z11: =IFERROR(VLOOKUP($W11,Plantilla!$B$3:$AE$2496,4,0),"") | AA11: =IFERROR(VLOOKUP($W11,Plantilla!$B$3:$AJ$2496,17,0),"") | AB11: =IFERROR(IF('(3)_Plan_de_Accion'!M79<>"",'(3)_Plan_de_Accion'!M79,""),"") | AC11: =IFERROR(IF('(3)_Plan_de_Accion'!Q79<>"",'(3)_Plan_de_Accion'!Q79,""),"")
A12: 09 | F12: =IFERROR(IF($J12<>"",F11,""),"") | G12: =IFERROR(IF($J12<>"",G11,""),"") | H12: =IFERROR(IF($J12<>"",H11,""),"") | I12: =IFERROR(IF($J12<>"",I11,""),"") | J12: =IFERROR(IF($B12<>"",J11,""),"") | R12: =IFERROR(IF($J12<>"",R11,""),"") | S12: =IFERROR(IF($J12<>"",S11,""),"") | T12: =IFERROR(IF($J12<>"",T11,""),"") | U12: =IFERROR(IF($J12<>"",U11,""),"") | V12: =IFERROR(IF($J12<>"",V11,""),"") | X12: =IFERROR(VLOOKUP($W12,Plantilla!$B$3:$AE$2497,2,0),"") | Y12: =IFERROR(VLOOKUP($W12,Plantilla!$B$3:$AE$2497,4,0),"") | Z12: =IFERROR(VLOOKUP($W12,Plantilla!$B$3:$AE$2496,4,0),"") | AA12: =IFERROR(VLOOKUP($W12,Plantilla!$B$3:$AJ$2496,17,0),"") | AB12: =IFERROR(IF('(3)_Plan_de_Accion'!M88<>"",'(3)_Plan_de_Accion'!M88,""),"") | AC12: =IFERROR(IF('(3)_Plan_de_Accion'!Q88<>"",'(3)_Plan_de_Accion'!Q88,""),"")
A13: 10 | F13: =IFERROR(IF($J13<>"",F12,""),"") | G13: =IFERROR(IF($J13<>"",G12,""),"") | H13: =IFERROR(IF($J13<>"",H12,""),"") | I13: =IFERROR(IF($J13<>"",I12,""),"") | J13: =IFERROR(IF($B13<>"",J12,""),"") | R13: =IFERROR(IF($J13<>"",R12,""),"") | S13: =IFERROR(IF($J13<>"",S12,""),"") | T13: =IFERROR(IF($J13<>"",T12,""),"") | U13: =IFERROR(IF($J13<>"",U12,""),"") | V13: =IFERROR(IF($J13<>"",V12,""),"") | X13: =IFERROR(VLOOKUP($W13,Plantilla!$B$3:$AE$2497,2,0),"") | Y13: =IFERROR(VLOOKUP($W13,Plantilla!$B$3:$AE$2497,4,0),"") | Z13: =IFERROR(VLOOKUP($W13,Plantilla!$B$3:$AE$2496,4,0),"") | AA13: =IFERROR(VLOOKUP($W13,Plantilla!$B$3:$AJ$2496,17,0),"") | AB13: =IFERROR(IF('(3)_Plan_de_Accion'!M97<>"",'(3)_Plan_de_Accion'!M97,""),"") | AC13: =IFERROR(IF('(3)_Plan_de_Accion'!Q97<>"",'(3)_Plan_de_Accion'!Q97,""),"")
A14: 11 | F14: =IFERROR(IF($J14<>"",F13,""),"") | G14: =IFERROR(IF($J14<>"",G13,""),"") | H14: =IFERROR(IF($J14<>"",H13,""),"") | I14: =IFERROR(IF($J14<>"",I13,""),"") | J14: =IFERROR(IF($B14<>"",J13,""),"") | R14: =IFERROR(IF($J14<>"",R13,""),"") | S14: =IFERROR(IF($J14<>"",S13,""),"") | T14: =IFERROR(IF($J14<>"",T13,""),"") | U14: =IFERROR(IF($J14<>"",U13,""),"") | V14: =IFERROR(IF($J14<>"",V13,""),"") | X14: =IFERROR(VLOOKUP($W14,Plantilla!$B$3:$AE$2497,2,0),"") | Y14: =IFERROR(VLOOKUP($W14,Plantilla!$B$3:$AE$2497,4,0),"") | Z14: =IFERROR(VLOOKUP($W14,Plantilla!$B$3:$AE$2496,4,0),"") | AA14: =IFERROR(VLOOKUP($W14,Plantilla!$B$3:$AJ$2496,17,0),"") | AB14: =IFERROR(IF('(3)_Plan_de_Accion'!M106<>"",'(3)_Plan_de_Accion'!M106,""),"") | AC14: =IFERROR(IF('(3)_Plan_de_Accion'!Q106<>"",'(3)_Plan_de_Accion'!Q106,""),"")
A15: 12 | F15: =IFERROR(IF($J15<>"",F14,""),"") | G15: =IFERROR(IF($J15<>"",G14,""),"") | H15: =IFERROR(IF($J15<>"",H14,""),"") | I15: =IFERROR(IF($J15<>"",I14,""),"") | J15: =IFERROR(IF($B15<>"",J14,""),"") | R15: =IFERROR(IF($J15<>"",R14,""),"") | S15: =IFERROR(IF($J15<>"",S14,""),"") | T15: =IFERROR(IF($J15<>"",T14,""),"") | U15: =IFERROR(IF($J15<>"",U14,""),"") | V15: =IFERROR(IF($J15<>"",V14,""),"") | X15: =IFERROR(VLOOKUP($W15,Plantilla!$B$3:$AE$2497,2,0),"") | Y15: =IFERROR(VLOOKUP($W15,Plantilla!$B$3:$AE$2497,4,0),"") | Z15: =IFERROR(VLOOKUP($W15,Plantilla!$B$3:$AE$2496,4,0),"") | AA15: =IFERROR(VLOOKUP($W15,Plantilla!$B$3:$AJ$2496,17,0),"") | AB15: =IFERROR(IF('(3)_Plan_de_Accion'!M115<>"",'(3)_Plan_de_Accion'!M115,""),"") | AC15: =IFERROR(IF('(3)_Plan_de_Accion'!Q115<>"",'(3)_Plan_de_Accion'!Q115,""),"")
A16: 13 | F16: =IFERROR(IF($J16<>"",F15,""),"") | G16: =IFERROR(IF($J16<>"",G15,""),"") | H16: =IFERROR(IF($J16<>"",H15,""),"") | I16: =IFERROR(IF($J16<>"",I15,""),"") | J16: =IFERROR(IF($B16<>"",J15,""),"") | R16: =IFERROR(IF($J16<>"",R15,""),"") | S16: =IFERROR(IF($J16<>"",S15,""),"") | T16: =IFERROR(IF($J16<>"",T15,""),"") | U16: =IFERROR(IF($J16<>"",U15,""),"") | V16: =IFERROR(IF($J16<>"",V15,""),"") | X16: =IFERROR(VLOOKUP($W16,Plantilla!$B$3:$AE$2497,2,0),"") | Y16: =IFERROR(VLOOKUP($W16,Plantilla!$B$3:$AE$2497,4,0),"") | Z16: =IFERROR(VLOOKUP($W16,Plantilla!$B$3:$AE$2496,4,0),"") | AA16: =IFERROR(VLOOKUP($W16,Plantilla!$B$3:$AJ$2496,17,0),"") | AB16: =IFERROR(IF('(3)_Plan_de_Accion'!M124<>"",'(3)_Plan_de_Accion'!M124,""),"") | AC16: =IFERROR(IF('(3)_Plan_de_Accion'!Q124<>"",'(3)_Plan_de_Accion'!Q124,""),"")
A17: 14 | F17: =IFERROR(IF($J17<>"",F16,""),"") | G17: =IFERROR(IF($J17<>"",G16,""),"") | H17: =IFERROR(IF($J17<>"",H16,""),"") | I17: =IFERROR(IF($J17<>"",I16,""),"") | J17: =IFERROR(IF($B17<>"",J16,""),"") | R17: =IFERROR(IF($J17<>"",R16,""),"") | S17: =IFERROR(IF($J17<>"",S16,""),"") | T17: =IFERROR(IF($J17<>"",T16,""),"") | U17: =IFERROR(IF($J17<>"",U16,""),"") | V17: =IFERROR(IF($J17<>"",V16,""),"") | X17: =IFERROR(VLOOKUP($W17,Plantilla!$B$3:$AE$2497,2,0),"") | Y17: =IFERROR(VLOOKUP($W17,Plantilla!$B$3:$AE$2497,4,0),"") | Z17: =IFERROR(VLOOKUP($W17,Plantilla!$B$3:$AE$2496,4,0),"") | AA17: =IFERROR(VLOOKUP($W17,Plantilla!$B$3:$AJ$2496,17,0),"") | AB17: =IFERROR(IF('(3)_Plan_de_Accion'!M133<>"",'(3)_Plan_de_Accion'!M133,""),"") | AC17: =IFERROR(IF('(3)_Plan_de_Accion'!Q133<>"",'(3)_Plan_de_Accion'!Q133,""),"")
A18: 15 | F18: =IFERROR(IF($J18<>"",F17,""),"") | G18: =IFERROR(IF($J18<>"",G17,""),"") | H18: =IFERROR(IF($J18<>"",H17,""),"") | I18: =IFERROR(IF($J18<>"",I17,""),"") | J18: =IFERROR(IF($B18<>"",J17,""),"") | R18: =IFERROR(IF($J18<>"",R17,""),"") | S18: =IFERROR(IF($J18<>"",S17,""),"") | T18: =IFERROR(IF($J18<>"",T17,""),"") | U18: =IFERROR(IF($J18<>"",U17,""),"") | V18: =IFERROR(IF($J18<>"",V17,""),"") | X18: =IFERROR(VLOOKUP($W18,Plantilla!$B$3:$AE$2497,2,0),"") | Y18: =IFERROR(VLOOKUP($W18,Plantilla!$B$3:$AE$2497,4,0),"") | Z18: =IFERROR(VLOOKUP($W18,Plantilla!$B$3:$AE$2496,4,0),"") | AA18: =IFERROR(VLOOKUP($W18,Plantilla!$B$3:$AJ$2496,17,0),"") | AB18: =IFERROR(IF('(3)_Plan_de_Accion'!M142<>"",'(3)_Plan_de_Accion'!M142,""),"") | AC18: =IFERROR(IF('(3)_Plan_de_Accion'!Q142<>"",'(3)_Plan_de_Accion'!Q142,""),"")
A19: 16 | F19: =IFERROR(IF($J19<>"",F18,""),"") | G19: =IFERROR(IF($J19<>"",G18,""),"") | H19: =IFERROR(IF($J19<>"",H18,""),"") | I19: =IFERROR(IF($J19<>"",I18,""),"") | J19: =IFERROR(IF($B19<>"",J18,""),"") | R19: =IFERROR(IF($J19<>"",R18,""),"") | S19: =IFERROR(IF($J19<>"",S18,""),"") | T19: =IFERROR(IF($J19<>"",T18,""),"") | U19: =IFERROR(IF($J19<>"",U18,""),"") | V19: =IFERROR(IF($J19<>"",V18,""),"") | X19: =IFERROR(VLOOKUP($W19,Plantilla!$B$3:$AE$2497,2,0),"") | Y19: =IFERROR(VLOOKUP($W19,Plantilla!$B$3:$AE$2497,4,0),"") | Z19: =IFERROR(VLOOKUP($W19,Plantilla!$B$3:$AE$2496,4,0),"") | AA19: =IFERROR(VLOOKUP($W19,Plantilla!$B$3:$AJ$2496,17,0),"") | AB19: =IFERROR(IF('(3)_Plan_de_Accion'!M151<>"",'(3)_Plan_de_Accion'!M151,""),"") | AC19: =IFERROR(IF('(3)_Plan_de_Accion'!Q151<>"",'(3)_Plan_de_Accion'!Q151,""),"")
A20: 17 | F20: =IFERROR(IF($J20<>"",F19,""),"") | G20: =IFERROR(IF($J20<>"",G19,""),"") | H20: =IFERROR(IF($J20<>"",H19,""),"") | I20: =IFERROR(IF($J20<>"",I19,""),"") | J20: =IFERROR(IF($B20<>"",J19,""),"") | R20: =IFERROR(IF($J20<>"",R19,""),"") | S20: =IFERROR(IF($J20<>"",S19,""),"") | T20: =IFERROR(IF($J20<>"",T19,""),"") | U20: =IFERROR(IF($J20<>"",U19,""),"") | V20: =IFERROR(IF($J20<>"",V19,""),"") | X20: =IFERROR(VLOOKUP($W20,Plantilla!$B$3:$AE$2497,2,0),"") | Y20: =IFERROR(VLOOKUP($W20,Plantilla!$B$3:$AE$2497,4,0),"") | Z20: =IFERROR(VLOOKUP($W20,Plantilla!$B$3:$AE$2496,4,0),"") | AA20: =IFERROR(VLOOKUP($W20,Plantilla!$B$3:$AJ$2496,17,0),"") | AB20: =IFERROR(IF('(3)_Plan_de_Accion'!M160<>"",'(3)_Plan_de_Accion'!M160,""),"") | AC20: =IFERROR(IF('(3)_Plan_de_Accion'!Q160<>"",'(3)_Plan_de_Accion'!Q160,""),"")
A21: 18 | F21: =IFERROR(IF($J21<>"",F20,""),"") | G21: =IFERROR(IF($J21<>"",G20,""),"") | H21: =IFERROR(IF($J21<>"",H20,""),"") | I21: =IFERROR(IF($J21<>"",I20,""),"") | J21: =IFERROR(IF($B21<>"",J20,""),"") | R21: =IFERROR(IF($J21<>"",R20,""),"") | S21: =IFERROR(IF($J21<>"",S20,""),"") | T21: =IFERROR(IF($J21<>"",T20,""),"") | U21: =IFERROR(IF($J21<>"",U20,""),"") | V21: =IFERROR(IF($J21<>"",V20,""),"") | X21: =IFERROR(VLOOKUP($W21,Plantilla!$B$3:$AE$2497,2,0),"") | Y21: =IFERROR(VLOOKUP($W21,Plantilla!$B$3:$AE$2497,4,0),"") | Z21: =IFERROR(VLOOKUP($W21,Plantilla!$B$3:$AE$2496,4,0),"") | AA21: =IFERROR(VLOOKUP($W21,Plantilla!$B$3:$AJ$2496,17,0),"") | AB21: =IFERROR(IF('(3)_Plan_de_Accion'!M169<>"",'(3)_Plan_de_Accion'!M169,""),"") | AC21: =IFERROR(IF('(3)_Plan_de_Accion'!Q169<>"",'(3)_Plan_de_Accion'!Q169,""),"")
A22: 19 | F22: =IFERROR(IF($J22<>"",F21,""),"") | G22: =IFERROR(IF($J22<>"",G21,""),"") | H22: =IFERROR(IF($J22<>"",H21,""),"") | I22: =IFERROR(IF($J22<>"",I21,""),"") | J22: =IFERROR(IF($B22<>"",J21,""),"") | R22: =IFERROR(IF($J22<>"",R21,""),"") | S22: =IFERROR(IF($J22<>"",S21,""),"") | T22: =IFERROR(IF($J22<>"",T21,""),"") | U22: =IFERROR(IF($J22<>"",U21,""),"") | V22: =IFERROR(IF($J22<>"",V21,""),"") | X22: =IFERROR(VLOOKUP($W22,Plantilla!$B$3:$AE$2497,2,0),"") | Y22: =IFERROR(VLOOKUP($W22,Plantilla!$B$3:$AE$2497,4,0),"") | Z22: =IFERROR(VLOOKUP($W22,Plantilla!$B$3:$AE$2496,4,0),"") | AA22: =IFERROR(VLOOKUP($W22,Plantilla!$B$3:$AJ$2496,17,0),"") | AB22: =IFERROR(IF('(3)_Plan_de_Accion'!M178<>"",'(3)_Plan_de_Accion'!M178,""),"") | AC22: =IFERROR(IF('(3)_Plan_de_Accion'!Q178<>"",'(3)_Plan_de_Accion'!Q178,""),"")
A23: 20 | F23: =IFERROR(IF($J23<>"",F22,""),"") | G23: =IFERROR(IF($J23<>"",G22,""),"") | H23: =IFERROR(IF($J23<>"",H22,""),"") | I23: =IFERROR(IF($J23<>"",I22,""),"") | J23: =IFERROR(IF($B23<>"",J22,""),"") | R23: =IFERROR(IF($J23<>"",R22,""),"") | S23: =IFERROR(IF($J23<>"",S22,""),"") | T23: =IFERROR(IF($J23<>"",T22,""),"") | U23: =IFERROR(IF($J23<>"",U22,""),"") | V23: =IFERROR(IF($J23<>"",V22,""),"") | X23: =IFERROR(VLOOKUP($W23,Plantilla!$B$3:$AE$2497,2,0),"") | Y23: =IFERROR(VLOOKUP($W23,Plantilla!$B$3:$AE$2497,4,0),"") | Z23: =IFERROR(VLOOKUP($W23,Plantilla!$B$3:$AE$2496,4,0),"") | AA23: =IFERROR(VLOOKUP($W23,Plantilla!$B$3:$AJ$2496,17,0),"") | AB23: =IFERROR(IF('(3)_Plan_de_Accion'!M187<>"",'(3)_Plan_de_Accion'!M187,""),"") | AC23: =IFERROR(IF('(3)_Plan_de_Accion'!Q187<>"",'(3)_Plan_de_Accion'!Q187,""),"")
A24: 21 | F24: =IFERROR(IF($J24<>"",F23,""),"") | G24: =IFERROR(IF($J24<>"",G23,""),"") | H24: =IFERROR(IF($J24<>"",H23,""),"") | I24: =IFERROR(IF($J24<>"",I23,""),"") | J24: =IFERROR(IF($B24<>"",J23,""),"") | R24: =IFERROR(IF($J24<>"",R23,""),"") | S24: =IFERROR(IF($J24<>"",S23,""),"") | T24: =IFERROR(IF($J24<>"",T23,""),"") | U24: =IFERROR(IF($J24<>"",U23,""),"") | V24: =IFERROR(IF($J24<>"",V23,""),"") | X24: =IFERROR(VLOOKUP($W24,Plantilla!$B$3:$AE$2497,2,0),"") | Y24: =IFERROR(VLOOKUP($W24,Plantilla!$B$3:$AE$2497,4,0),"") | Z24: =IFERROR(VLOOKUP($W24,Plantilla!$B$3:$AE$2496,4,0),"") | AA24: =IFERROR(VLOOKUP($W24,Plantilla!$B$3:$AJ$2496,17,0),"") | AB24: =IFERROR(IF('(3)_Plan_de_Accion'!M196<>"",'(3)_Plan_de_Accion'!M196,""),"") | AC24: =IFERROR(IF('(3)_Plan_de_Accion'!Q196<>"",'(3)_Plan_de_Accion'!Q196,""),"")
A25: 22 | F25: =IFERROR(IF($J25<>"",F24,""),"") | G25: =IFERROR(IF($J25<>"",G24,""),"") | H25: =IFERROR(IF($J25<>"",H24,""),"") | I25: =IFERROR(IF($J25<>"",I24,""),"") | J25: =IFERROR(IF($B25<>"",J24,""),"") | R25: =IFERROR(IF($J25<>"",R24,""),"") | S25: =IFERROR(IF($J25<>"",S24,""),"") | T25: =IFERROR(IF($J25<>"",T24,""),"") | U25: =IFERROR(IF($J25<>"",U24,""),"") | V25: =IFERROR(IF($J25<>"",V24,""),"") | X25: =IFERROR(VLOOKUP($W25,Plantilla!$B$3:$AE$2497,2,0),"") | Y25: =IFERROR(VLOOKUP($W25,Plantilla!$B$3:$AE$2497,4,0),"") | Z25: =IFERROR(VLOOKUP($W25,Plantilla!$B$3:$AE$2496,4,0),"") | AA25: =IFERROR(VLOOKUP($W25,Plantilla!$B$3:$AJ$2496,17,0),"") | AB25: =IFERROR(IF('(3)_Plan_de_Accion'!M205<>"",'(3)_Plan_de_Accion'!M205,""),"") | AC25: =IFERROR(IF('(3)_Plan_de_Accion'!Q205<>"",'(3)_Plan_de_Accion'!Q205,""),"")
A26: 23 | F26: =IFERROR(IF($J26<>"",F25,""),"") | G26: =IFERROR(IF($J26<>"",G25,""),"") | H26: =IFERROR(IF($J26<>"",H25,""),"") | I26: =IFERROR(IF($J26<>"",I25,""),"") | J26: =IFERROR(IF($B26<>"",J25,""),"") | R26: =IFERROR(IF($J26<>"",R25,""),"") | S26: =IFERROR(IF($J26<>"",S25,""),"") | T26: =IFERROR(IF($J26<>"",T25,""),"") | U26: =IFERROR(IF($J26<>"",U25,""),"") | V26: =IFERROR(IF($J26<>"",V25,""),"") | X26: =IFERROR(VLOOKUP($W26,Plantilla!$B$3:$AE$2497,2,0),"") | Y26: =IFERROR(VLOOKUP($W26,Plantilla!$B$3:$AE$2497,4,0),"") | Z26: =IFERROR(VLOOKUP($W26,Plantilla!$B$3:$AE$2496,4,0),"") | AA26: =IFERROR(VLOOKUP($W26,Plantilla!$B$3:$AJ$2496,17,0),"") | AB26: =IFERROR(IF('(3)_Plan_de_Accion'!M214<>"",'(3)_Plan_de_Accion'!M214,""),"") | AC26: =IFERROR(IF('(3)_Plan_de_Accion'!Q214<>"",'(3)_Plan_de_Accion'!Q214,""),"")
A27: 24 | F27: =IFERROR(IF($J27<>"",F26,""),"") | G27: =IFERROR(IF($J27<>"",G26,""),"") | H27: =IFERROR(IF($J27<>"",H26,""),"") | I27: =IFERROR(IF($J27<>"",I26,""),"") | J27: =IFERROR(IF($B27<>"",J26,""),"") | R27: =IFERROR(IF($J27<>"",R26,""),"") | S27: =IFERROR(IF($J27<>"",S26,""),"") | T27: =IFERROR(IF($J27<>"",T26,""),"") | U27: =IFERROR(IF($J27<>"",U26,""),"") | V27: =IFERROR(IF($J27<>"",V26,""),"") | X27: =IFERROR(VLOOKUP($W27,Plantilla!$B$3:$AE$2497,2,0),"") | Y27: =IFERROR(VLOOKUP($W27,Plantilla!$B$3:$AE$2497,4,0),"") | Z27: =IFERROR(VLOOKUP($W27,Plantilla!$B$3:$AE$2496,4,0),"") | AA27: =IFERROR(VLOOKUP($W27,Plantilla!$B$3:$AJ$2496,17,0),"") | AB27: =IFERROR(IF('(3)_Plan_de_Accion'!M223<>"",'(3)_Plan_de_Accion'!M223,""),"") | AC27: =IFERROR(IF('(3)_Plan_de_Accion'!Q223<>"",'(3)_Plan_de_Accion'!Q223,""),"")
A28: 25 | F28: =IFERROR(IF($J28<>"",F27,""),"") | G28: =IFERROR(IF($J28<>"",G27,""),"") | H28: =IFERROR(IF($J28<>"",H27,""),"") | I28: =IFERROR(IF($J28<>"",I27,""),"") | J28: =IFERROR(IF($B28<>"",J27,""),"") | R28: =IFERROR(IF($J28<>"",R27,""),"") | S28: =IFERROR(IF($J28<>"",S27,""),"") | T28: =IFERROR(IF($J28<>"",T27,""),"") | U28: =IFERROR(IF($J28<>"",U27,""),"") | V28: =IFERROR(IF($J28<>"",V27,""),"") | X28: =IFERROR(VLOOKUP($W28,Plantilla!$B$3:$AE$2497,2,0),"") | Y28: =IFERROR(VLOOKUP($W28,Plantilla!$B$3:$AE$2497,4,0),"") | Z28: =IFERROR(VLOOKUP($W28,Plantilla!$B$3:$AE$2496,4,0),"") | AA28: =IFERROR(VLOOKUP($W28,Plantilla!$B$3:$AJ$2496,17,0),"") | AB28: =IFERROR(IF('(3)_Plan_de_Accion'!M232<>"",'(3)_Plan_de_Accion'!M232,""),"") | AC28: =IFERROR(IF('(3)_Plan_de_Accion'!Q232<>"",'(3)_Plan_de_Accion'!Q232,""),"")
A29: 26 | F29: =IFERROR(IF($J29<>"",F28,""),"") | G29: =IFERROR(IF($J29<>"",G28,""),"") | H29: =IFERROR(IF($J29<>"",H28,""),"") | I29: =IFERROR(IF($J29<>"",I28,""),"") | J29: =IFERROR(IF($B29<>"",J28,""),"") | R29: =IFERROR(IF($J29<>"",R28,""),"") | S29: =IFERROR(IF($J29<>"",S28,""),"") | T29: =IFERROR(IF($J29<>"",T28,""),"") | U29: =IFERROR(IF($J29<>"",U28,""),"") | V29: =IFERROR(IF($J29<>"",V28,""),"") | X29: =IFERROR(VLOOKUP($W29,Plantilla!$B$3:$AE$2497,2,0),"") | Y29: =IFERROR(VLOOKUP($W29,Plantilla!$B$3:$AE$2497,4,0),"") | Z29: =IFERROR(VLOOKUP($W29,Plantilla!$B$3:$AE$2496,4,0),"") | AA29: =IFERROR(VLOOKUP($W29,Plantilla!$B$3:$AJ$2496,17,0),"") | AB29: =IFERROR(IF('(3)_Plan_de_Accion'!M241<>"",'(3)_Plan_de_Accion'!M241,""),"") | AC29: =IFERROR(IF('(3)_Plan_de_Accion'!Q241<>"",'(3)_Plan_de_Accion'!Q241,""),"")
A30: 27 | F30: =IFERROR(IF($J30<>"",F29,""),"") | G30: =IFERROR(IF($J30<>"",G29,""),"") | H30: =IFERROR(IF($J30<>"",H29,""),"") | I30: =IFERROR(IF($J30<>"",I29,""),"") | J30: =IFERROR(IF($B30<>"",J29,""),"") | R30: =IFERROR(IF($J30<>"",R29,""),"") | S30: =IFERROR(IF($J30<>"",S29,""),"") | T30: =IFERROR(IF($J30<>"",T29,""),"") | U30: =IFERROR(IF($J30<>"",U29,""),"") | V30: =IFERROR(IF($J30<>"",V29,""),"") | X30: =IFERROR(VLOOKUP($W30,Plantilla!$B$3:$AE$2497,2,0),"") | Y30: =IFERROR(VLOOKUP($W30,Plantilla!$B$3:$AE$2497,4,0),"") | Z30: =IFERROR(VLOOKUP($W30,Plantilla!$B$3:$AE$2496,4,0),"") | AA30: =IFERROR(VLOOKUP($W30,Plantilla!$B$3:$AJ$2496,17,0),"") | AB30: =IFERROR(IF('(3)_Plan_de_Accion'!M250<>"",'(3)_Plan_de_Accion'!M250,""),"") | AC30: =IFERROR(IF('(3)_Plan_de_Accion'!Q250<>"",'(3)_Plan_de_Accion'!Q250,""),"")
A31: 28 | F31: =IFERROR(IF($J31<>"",F30,""),"") | G31: =IFERROR(IF($J31<>"",G30,""),"") | H31: =IFERROR(IF($J31<>"",H30,""),"") | I31: =IFERROR(IF($J31<>"",I30,""),"") | J31: =IFERROR(IF($B31<>"",J30,""),"") | R31: =IFERROR(IF($J31<>"",R30,""),"") | S31: =IFERROR(IF($J31<>"",S30,""),"") | T31: =IFERROR(IF($J31<>"",T30,""),"") | U31: =IFERROR(IF($J31<>"",U30,""),"") | V31: =IFERROR(IF($J31<>"",V30,""),"") | X31: =IFERROR(VLOOKUP($W31,Plantilla!$B$3:$AE$2497,2,0),"") | Y31: =IFERROR(VLOOKUP($W31,Plantilla!$B$3:$AE$2497,4,0),"") | Z31: =IFERROR(VLOOKUP($W31,Plantilla!$B$3:$AE$2496,4,0),"") | AA31: =IFERROR(VLOOKUP($W31,Plantilla!$B$3:$AJ$2496,17,0),"") | AB31: =IFERROR(IF('(3)_Plan_de_Accion'!M259<>"",'(3)_Plan_de_Accion'!M259,""),"") | AC31: =IFERROR(IF('(3)_Plan_de_Accion'!Q259<>"",'(3)_Plan_de_Accion'!Q259,""),"")
A32: 29 | F32: =IFERROR(IF($J32<>"",F31,""),"") | G32: =IFERROR(IF($J32<>"",G31,""),"") | H32: =IFERROR(IF($J32<>"",H31,""),"") | I32: =IFERROR(IF($J32<>"",I31,""),"") | J32: =IFERROR(IF($B32<>"",J31,""),"") | R32: =IFERROR(IF($J32<>"",R31,""),"") | S32: =IFERROR(IF($J32<>"",S31,""),"") | T32: =IFERROR(IF($J32<>"",T31,""),"") | U32: =IFERROR(IF($J32<>"",U31,""),"") | V32: =IFERROR(IF($J32<>"",V31,""),"") | X32: =IFERROR(VLOOKUP($W32,Plantilla!$B$3:$AE$2497,2,0),"") | Y32: =IFERROR(VLOOKUP($W32,Plantilla!$B$3:$AE$2497,4,0),"") | Z32: =IFERROR(VLOOKUP($W32,Plantilla!$B$3:$AE$2496,4,0),"") | AA32: =IFERROR(VLOOKUP($W32,Plantilla!$B$3:$AJ$2496,17,0),"") | AB32: =IFERROR(IF('(3)_Plan_de_Accion'!M268<>"",'(3)_Plan_de_Accion'!M268,""),"") | AC32: =IFERROR(IF('(3)_Plan_de_Accion'!Q268<>"",'(3)_Plan_de_Accion'!Q268,""),"")
A33: 30 | F33: =IFERROR(IF($J33<>"",F32,""),"") | G33: =IFERROR(IF($J33<>"",G32,""),"") | H33: =IFERROR(IF($J33<>"",H32,""),"") | I33: =IFERROR(IF($J33<>"",I32,""),"") | J33: =IFERROR(IF($B33<>"",J32,""),"") | R33: =IFERROR(IF($J33<>"",R32,""),"") | S33: =IFERROR(IF($J33<>"",S32,""),"") | T33: =IFERROR(IF($J33<>"",T32,""),"") | U33: =IFERROR(IF($J33<>"",U32,""),"") | V33: =IFERROR(IF($J33<>"",V32,""),"") | X33: =IFERROR(VLOOKUP($W33,Plantilla!$B$3:$AE$2497,2,0),"") | Y33: =IFERROR(VLOOKUP($W33,Plantilla!$B$3:$AE$2497,4,0),"") | Z33: =IFERROR(VLOOKUP($W33,Plantilla!$B$3:$AE$2496,4,0),"") | AA33: =IFERROR(VLOOKUP($W33,Plantilla!$B$3:$AJ$2496,17,0),"") | AB33: =IFERROR(IF('(3)_Plan_de_Accion'!M277<>"",'(3)_Plan_de_Accion'!M277,""),"") | AC33: =IFERROR(IF('(3)_Plan_de_Accion'!Q277<>"",'(3)_Plan_de_Accion'!Q277,""),"")

Sheet (3)_Plan_de_Accion
F2: PLAN DE ACCIÓN CORRECTIVA PARA ATENDER LOS HALLAZGOS Y RECOMENDACIONES
B5: Empresa | E5: Banco Base | G5: a | H5: Arrendadora Base | K5: Casa de Bolsa Base | N5: GFBASE
AF6: ACEPTABLE | AI6: ANTONIO FLORES LUNA | AJ6: Director de Auditoría Interna
A7: Cifras al | C7: =IFERROR(IF('(1)_Base_de_Datos'!I4<>"",'(1)_Base_de_Datos'!I4,""),"") | G7: Periodo de Revisión: | J7: =IFERROR(IF('(1)_Base_de_Datos'!H4<>"",'(1)_Base_de_Datos'!H4,""),"") | Q7: Fecha de elaboración | R7: =IFERROR(IF('(1)_Base_de_Datos'!V4<>"",'(1)_Base_de_Datos'!V4,""),"") | U7: EN CASO DE REALIZAR COMENTARIOS ADICIONALES, COMO OBJETIVOS, CARACTERÍSTICAS, ETC., MOSTRAR LAS CELDAS 10 A LA 15 QUE ESTÁN OCULTAS. | AF7: PARCIALMENTE ACEPTABLE | AI7: CARLOS ALBERTO NAVARRO RIVERA | AJ7: Subdirección de Auditoría Procesos de Staff y Riesgos
G8: =IF(J8<>"","Proceso Auditado", "") | J8: =IFERROR(IF('(1)_Base_de_Datos'!J4<>"",'(1)_Base_de_Datos'!J4,""),"") | AF8: INACEPTABLE
G9: =IF(J9<>"","Nombre del Monitoreo", "") | J9: =IFERROR(IF('(1)_Base_de_Datos'!K4<>"",'(1)_Base_de_Datos'!K4,""),"") | P9: Auditor | Q9: =IFERROR(IF('(1)_Base_de_Datos'!T4<>"",'(1)_Base_de_Datos'!T4,""),"") | AF9: Resultado2
A11: A U D I T O R Í A | M11: Á R E A A U D I T A D A
A12: No. | B12: HALLAZGO | G12: GRADO DE RIESGO | H12: IMPLICACIÓN/ FUNDAMENTO | L12: TIPO DE HALLAZGO | M12: COMPROMISO | Q12: FECHA COMPROMISO | R12: RESPONSABLE | S12: PUESTO RESPONSABLE
B13: =IF('(1)_Base_de_Datos'!$R$4<>"",'(1)_Base_de_Datos'!$R$4,"") | H13: =IF('(1)_Base_de_Datos'!$B$4="Recomendación",'(1)_Base_de_Datos'!$B$4,"")
A14: 1 | B14: =IFERROR(IF('(1)_Base_de_Datos'!L4<>"",'(1)_Base_de_Datos'!L4,""),"") | G14: =IFERROR(IF('(1)_Base_de_Datos'!C4<>"",'(1)_Base_de_Datos'!C4,""),"") | H14: IMPLICACIÓN | L14: =IFERROR(IF('(1)_Base_de_Datos'!Q4<>"",'(1)_Base_de_Datos'!Q4,""),"") | M14: Se corregirá la clasificación sectorial identificada y el cálculo de la exposición y reserva; adicionalmente, se reforzarán las validaciones previas al cierre para asegurar la correcta determinación de PI, SP y reservas. | R14: =IFERROR(IF('(1)_Base_de_Datos'!X4<>"",'(1)_Base_de_Datos'!X4,""),"") | S14: =IFERROR(IF('(1)_Base_de_Datos'!Y4<>"",'(1)_Base_de_Datos'!Y4,""),"")
B15: =IFERROR(IF('(1)_Base_de_Datos'!M4<>"",'(1)_Base_de_Datos'!M4,""),"") | H15: =IFERROR(IF('(1)_Base_de_Datos'!N4<>"",'(1)_Base_de_Datos'!N4,""),"")
H17: FUNDAMENTO
H18: =IFERROR(IF('(1)_Base_de_Datos'!O4<>"",'(1)_Base_de_Datos'!O4,""),"")
H20: CONTROL
H21: =IFERROR(IF('(1)_Base_de_Datos'!P4<>"",'(1)_Base_de_Datos'!P4,""),"")
B22: =IF('(1)_Base_de_Datos'!$R$5<>"",'(1)_Base_de_Datos'!$R$5,"") | H22: =IF('(1)_Base_de_Datos'!$B$5="Recomendación",'(1)_Base_de_Datos'!$B$5,"")
A23: 2 | B23: =IFERROR(IF('(1)_Base_de_Datos'!L5<>"",'(1)_Base_de_Datos'!L5,""),"") | G23: =IFERROR(IF('(1)_Base_de_Datos'!C5<>"",'(1)_Base_de_Datos'!C5,""),"") | H23: IMPLICACIÓN | L23: =IFERROR(IF('(1)_Base_de_Datos'!Q5<>"",'(1)_Base_de_Datos'!Q5,""),"") | M23: Se corregirá el valor reportado en el campo 45 del R04-C-0438 conforme al instructivo vigente y se incorporará una validación previa al envío para asegurar la calidad de la información regulatoria. | R23: =IFERROR(IF('(1)_Base_de_Datos'!X5<>"",'(1)_Base_de_Datos'!X5,""),"") | S23: =IFERROR(IF('(1)_Base_de_Datos'!Y5<>"",'(1)_Base_de_Datos'!Y5,""),"")
B24: =IFERROR(IF('(1)_Base_de_Datos'!M5<>"",'(1)_Base_de_Datos'!M5,""),"") | H24: =IFERROR(IF('(1)_Base_de_Datos'!N5<>"",'(1)_Base_de_Datos'!N5,""),"")
H26: FUNDAMENTO
H27: =IFERROR(IF('(1)_Base_de_Datos'!O5<>"",'(1)_Base_de_Datos'!O5,""),"")
H29: CONTROL
H30: =IFERROR(IF('(1)_Base_de_Datos'!P5<>"",'(1)_Base_de_Datos'!P5,""),"")
B31: =IF('(1)_Base_de_Datos'!$R$6<>"",'(1)_Base_de_Datos'!$R$6,"") | H31: =IF('(1)_Base_de_Datos'!$B$6="Recomendación",'(1)_Base_de_Datos'!$B$6,"")
A32: 3 | B32: =IFERROR(IF('(1)_Base_de_Datos'!L6<>"",'(1)_Base_de_Datos'!L6,""),"") | G32: =IFERROR(IF('(1)_Base_de_Datos'!C6<>"",'(1)_Base_de_Datos'!C6,""),"") | H32: IMPLICACIÓN | L32: =IFERROR(IF('(1)_Base_de_Datos'!Q6<>"",'(1)_Base_de_Datos'!Q6,""),"") | R32: =IFERROR(IF('(1)_Base_de_Datos'!X6<>"",'(1)_Base_de_Datos'!X6,""),"") | S32: =IFERROR(IF('(1)_Base_de_Datos'!Y6<>"",'(1)_Base_de_Datos'!Y6,""),"")
B33: =IFERROR(IF('(1)_Base_de_Datos'!M6<>"",'(1)_Base_de_Datos'!M6,""),"") | H33: =IFERROR(IF('(1)_Base_de_Datos'!N6<>"",'(1)_Base_de_Datos'!N6,""),"")
H35: FUNDAMENTO
H36: =IFERROR(IF('(1)_Base_de_Datos'!O6<>"",'(1)_Base_de_Datos'!O6,""),"")
H38: CONTROL
H39: =IFERROR(IF('(1)_Base_de_Datos'!P6<>"",'(1)_Base_de_Datos'!P6,""),"")
B40: =IF('(1)_Base_de_Datos'!$R$7<>"",'(1)_Base_de_Datos'!$R$7,"") | H40: =IF('(1)_Base_de_Datos'!$B$7="Recomendación",'(1)_Base_de_Datos'!$B$7,"")
A41: 4 | B41: =IFERROR(IF('(1)_Base_de_Datos'!L7<>"",'(1)_Base_de_Datos'!L7,""),"") | G41: =IFERROR(IF('(1)_Base_de_Datos'!C7<>"",'(1)_Base_de_Datos'!C7,""),"") | H41: IMPLICACIÓN | L41: =IFERROR(IF('(1)_Base_de_Datos'!Q7<>"",'(1)_Base_de_Datos'!Q7,""),"") | R41: =IFERROR(IF('(1)_Base_de_Datos'!X7<>"",'(1)_Base_de_Datos'!X7,""),"") | S41: =IFERROR(IF('(1)_Base_de_Datos'!Y7<>"",'(1)_Base_de_Datos'!Y7,""),"")
B42: =IFERROR(IF('(1)_Base_de_Datos'!M7<>"",'(1)_Base_de_Datos'!M7,""),"") | H42: =IFERROR(IF('(1)_Base_de_Datos'!N7<>"",'(1)_Base_de_Datos'!N7,""),"")
H44: FUNDAMENTO
H45: =IFERROR(IF('(1)_Base_de_Datos'!O7>"",'(1)_Base_de_Datos'!O7,""),"")
H47: CONTROL
H48: =IFERROR(IF('(1)_Base_de_Datos'!P7<>"",'(1)_Base_de_Datos'!P7,""),"")
B49: =IF('(1)_Base_de_Datos'!$R$8<>"",'(1)_Base_de_Datos'!$R$8,"") | H49: =IF('(1)_Base_de_Datos'!$B$8="Recomendación",'(1)_Base_de_Datos'!$B$8,"")
A50: 5 | B50: =IFERROR(IF('(1)_Base_de_Datos'!L8<>"",'(1)_Base_de_Datos'!L8,""),"") | G50: =IFERROR(IF('(1)_Base_de_Datos'!C8<>"",'(1)_Base_de_Datos'!C8,""),"") | H50: IMPLICACIÓN | L50: =IFERROR(IF('(1)_Base_de_Datos'!Q8<>"",'(1)_Base_de_Datos'!Q8,""),"") | R50: =IFERROR(IF('(1)_Base_de_Datos'!X8<>"",'(1)_Base_de_Datos'!X8,""),"") | S50: =IFERROR(IF('(1)_Base_de_Datos'!Y8<>"",'(1)_Base_de_Datos'!Y8,""),"")
B51: =IFERROR(IF('(1)_Base_de_Datos'!M8<>"",'(1)_Base_de_Datos'!M8,""),"") | H51: =IFERROR(IF('(1)_Base_de_Datos'!N8<>"",'(1)_Base_de_Datos'!N8,""),"")
H53: FUNDAMENTO
H54: =IFERROR(IF('(1)_Base_de_Datos'!O8<>"",'(1)_Base_de_Datos'!O8,""),"")
H56: CONTROL
H57: =IFERROR(IF('(1)_Base_de_Datos'!P8<>"",'(1)_Base_de_Datos'!P8,""),"")
B58: =IF('(1)_Base_de_Datos'!$R$9<>"",'(1)_Base_de_Datos'!$R$9,"") | H58: =IF('(1)_Base_de_Datos'!$B$9="Recomendación",'(1)_Base_de_Datos'!$B$9,"")
A59: 6 | B59: =IFERROR(IF('(1)_Base_de_Datos'!L9<>"",'(1)_Base_de_Datos'!L9,""),"") | G59: =IFERROR(IF('(1)_Base_de_Datos'!C9<>"",'(1)_Base_de_Datos'!C9,""),"") | H59: IMPLICACIÓN | L59: =IFERROR(IF('(1)_Base_de_Datos'!Q9<>"",'(1)_Base_de_Datos'!Q9,""),"") | R59: =IFERROR(IF('(1)_Base_de_Datos'!X9<>"",'(1)_Base_de_Datos'!X9,""),"") | S59: =IFERROR(IF('(1)_Base_de_Datos'!Y9<>"",'(1)_Base_de_Datos'!Y9,""),"")
B60: =IFERROR(IF('(1)_Base_de_Datos'!M9<>"",'(1)_Base_de_Datos'!M9,""),"") | H60: =IFERROR(IF('(1)_Base_de_Datos'!N9<>"",'(1)_Base_de_Datos'!N9,""),"")
H62: FUNDAMENTO
H63: =IFERROR(IF('(1)_Base_de_Datos'!O9<>"",'(1)_Base_de_Datos'!O9,""),"")
H65: CONTROL
H66: =IFERROR(IF('(1)_Base_de_Datos'!P9<>"",'(1)_Base_de_Datos'!P9,""),"")
B67: =IF('(1)_Base_de_Datos'!$R$10<>"",'(1)_Base_de_Datos'!$R$10,"") | H67: =IF('(1)_Base_de_Datos'!$B$10="Recomendación",'(1)_Base_de_Datos'!$B$10,"")
A68: 7 | B68: =IFERROR(IF('(1)_Base_de_Datos'!L10<>"",'(1)_Base_de_Datos'!L10,""),"") | G68: =IFERROR(IF('(1)_Base_de_Datos'!C10<>"",'(1)_Base_de_Datos'!C10,""),"") | H68: IMPLICACIÓN | L68: =IFERROR(IF('(1)_Base_de_Datos'!Q10<>"",'(1)_Base_de_Datos'!Q10,""),"") | R68: =IFERROR(IF('(1)_Base_de_Datos'!X10<>"",'(1)_Base_de_Datos'!X10,""),"") | S68: =IFERROR(IF('(1)_Base_de_Datos'!Y10<>"",'(1)_Base_de_Datos'!Y10,""),"")
B69: =IFERROR(IF('(1)_Base_de_Datos'!M10<>"",'(1)_Base_de_Datos'!M10,""),"") | H69: =IFERROR(IF('(1)_Base_de_Datos'!N10<>"",'(1)_Base_de_Datos'!N10,""),"")
H71: FUNDAMENTO
H72: =IFERROR(IF('(1)_Base_de_Datos'!O10<>"",'(1)_Base_de_Datos'!O10,""),"")
H76: CONTROL
H77: =IFERROR(IF('(1)_Base_de_Datos'!P10<>"",'(1)_Base_de_Datos'!P10,""),"")
B78: =IF('(1)_Base_de_Datos'!$R$11<>"",'(1)_Base_de_Datos'!$R$11,"") | H78: =IF('(1)_Base_de_Datos'!$B$11="Recomendación",'(1)_Base_de_Datos'!$B$11,"")
A79: 8 | B79: =IFERROR(IF('(1)_Base_de_Datos'!L11<>"",'(1)_Base_de_Datos'!L11,""),"") | G79: =IFERROR(IF('(1)_Base_de_Datos'!C11<>"",'(1)_Base_de_Datos'!C11,""),"") | H79: IMPLICACIÓN | L79: =IFERROR(IF('(1)_Base_de_Datos'!Q11<>"",'(1)_Base_de_Datos'!Q11,""),"") | R79: =IFERROR(IF('(1)_Base_de_Datos'!X11<>"",'(1)_Base_de_Datos'!X11,""),"") | S79: =IFERROR(IF('(1)_Base_de_Datos'!Y11<>"",'(1)_Base_de_Datos'!Y11,""),"")
B80: =IFERROR(IF('(1)_Base_de_Datos'!M11<>"",'(1)_Base_de_Datos'!M11,""),"") | H80: =IFERROR(IF('(1)_Base_de_Datos'!N11<>"",'(1)_Base_de_Datos'!N11,""),"")
H82: FUNDAMENTO
H83: =IFERROR(IF('(1)_Base_de_Datos'!O11<>"",'(1)_Base_de_Datos'!O11,""),"")
H85: CONTROL
H86: =IFERROR(IF('(1)_Base_de_Datos'!P11<>"",'(1)_Base_de_Datos'!P11,""),"")
B87: =IF('(1)_Base_de_Datos'!$R$12<>"",'(1)_Base_de_Datos'!$R$12,"") | H87: =IF('(1)_Base_de_Datos'!$B$12="Recomendación",'(1)_Base_de_Datos'!$B$12,"")
A88: 9 | B88: =IFERROR(IF('(1)_Base_de_Datos'!L12<>"",'(1)_Base_de_Datos'!L12,""),"") | G88: =IFERROR(IF('(1)_Base_de_Datos'!C12<>"",'(1)_Base_de_Datos'!C12,""),"") | H88: IMPLICACIÓN | L88: =IFERROR(IF('(1)_Base_de_Datos'!Q12<>"",'(1)_Base_de_Datos'!Q12,""),"") | R88: =IFERROR(IF('(1)_Base_de_Datos'!X12<>"",'(1)_Base_de_Datos'!X12,""),"") | S88: =IFERROR(IF('(1)_Base_de_Datos'!Y12<>"",'(1)_Base_de_Datos'!Y12,""),"")
B89: =IFERROR(IF('(1)_Base_de_Datos'!M12<>"",'(1)_Base_de_Datos'!M12,""),"") | H89: =IFERROR(IF('(1)_Base_de_Datos'!N12<>"",'(1)_Base_de_Datos'!N12,""),"")
H91: FUNDAMENTO
H92: =IFERROR(IF('(1)_Base_de_Datos'!O12<>"",'(1)_Base_de_Datos'!O12,""),"")
H94: CONTROL
H95: =IFERROR(IF('(1)_Base_de_Datos'!P12<>"",'(1)_Base_de_Datos'!P12,""),"")
B96: =IF('(1)_Base_de_Datos'!$R$13<>"",'(1)_Base_de_Datos'!$R$13,"") | H96: =IF('(1)_Base_de_Datos'!$B$13="Recomendación",'(1)_Base_de_Datos'!$B$13,"")
A97: 10 | B97: =IFERROR(IF('(1)_Base_de_Datos'!L13<>"",'(1)_Base_de_Datos'!L13,""),"") | G97: =IFERROR(IF('(1)_Base_de_Datos'!C13<>"",'(1)_Base_de_Datos'!C13,""),"") | H97: IMPLICACIÓN | L97: =IFERROR(IF('(1)_Base_de_Datos'!Q13<>"",'(1)_Base_de_Datos'!Q13,""),"") | R97: =IFERROR(IF('(1)_Base_de_Datos'!X13<>"",'(1)_Base_de_Datos'!X13,""),"") | S97: =IFERROR(IF('(1)_Base_de_Datos'!Y13<>"",'(1)_Base_de_Datos'!Y13,""),"")
B98: =IFERROR(IF('(1)_Base_de_Datos'!M13<>"",'(1)_Base_de_Datos'!M13,""),"") | H98: =IFERROR(IF('(1)_Base_de_Datos'!N13<>"",'(1)_Base_de_Datos'!N13,""),"")
U99: EN CASO DE NECESITAR MAS HALLAZGOS, MOSTRAR LAS CELDAS 88 A 227 QUE ESTÁN OCULTAS.
H100: FUNDAMENTO
H101: =IFERROR(IF('(1)_Base_de_Datos'!O13<>"",'(1)_Base_de_Datos'!O13,""),"")
H103: CONTROL
H104: =IFERROR(IF('(1)_Base_de_Datos'!P13<>"",'(1)_Base_de_Datos'!P13,""),"")
B105: =IF('(1)_Base_de_Datos'!$R$14<>"",'(1)_Base_de_Datos'!$R$14,"") | H105: =IF('(1)_Base_de_Datos'!$B$14="Recomendación",'(1)_Base_de_Datos'!$B$14,"")
A106: 11 | B106: =IFERROR(IF('(1)_Base_de_Datos'!L14<>"",'(1)_Base_de_Datos'!L14,""),"") | G106: =IFERROR(IF('(1)_Base_de_Datos'!C14<>"",'(1)_Base_de_Datos'!C14,""),"") | H106: IMPLICACIÓN | L106: =IFERROR(IF('(1)_Base_de_Datos'!Q14<>"",'(1)_Base_de_Datos'!Q14,""),"") | R106: =IFERROR(IF('(1)_Base_de_Datos'!X14<>"",'(1)_Base_de_Datos'!X14,""),"") | S106: =IFERROR(IF('(1)_Base_de_Datos'!Y14<>"",'(1)_Base_de_Datos'!Y14,""),"")
B107: =IFERROR(IF('(1)_Base_de_Datos'!M14<>"",'(1)_Base_de_Datos'!M14,""),"") | H107: =IFERROR(IF('(1)_Base_de_Datos'!N14<>"",'(1)_Base_de_Datos'!N14,""),"")
H109: FUNDAMENTO
H110: =IFERROR(IF('(1)_Base_de_Datos'!O14<>"",'(1)_Base_de_Datos'!O14,""),"")
H112: CONTROL
H113: =IFERROR(IF('(1)_Base_de_Datos'!P14<>"",'(1)_Base_de_Datos'!P14,""),"")
B114: =IF('(1)_Base_de_Datos'!$R$15<>"",'(1)_Base_de_Datos'!$R$15,"") | H114: =IF('(1)_Base_de_Datos'!$B$15="Recomendación",'(1)_Base_de_Datos'!$B$15,"")
A115: 12 | B115: =IFERROR(IF('(1)_Base_de_Datos'!L15<>"",'(1)_Base_de_Datos'!L15,""),"") | G115: =IFERROR(IF('(1)_Base_de_Datos'!C15<>"",'(1)_Base_de_Datos'!C15,""),"") | H115: IMPLICACIÓN | L115: =IFERROR(IF('(1)_Base_de_Datos'!Q15<>"",'(1)_Base_de_Datos'!Q15,""),"") | R115: =IFERROR(IF('(1)_Base_de_Datos'!X15<>"",'(1)_Base_de_Datos'!X15,""),"") | S115: =IFERROR(IF('(1)_Base_de_Datos'!Y15<>"",'(1)_Base_de_Datos'!Y15,""),"")
B116: =IFERROR(IF('(1)_Base_de_Datos'!M15<>"",'(1)_Base_de_Datos'!M15,""),"") | H116: =IFERROR(IF('(1)_Base_de_Datos'!N15<>"",'(1)_Base_de_Datos'!N15,""),"")
H118: FUNDAMENTO
H119: =IFERROR(IF('(1)_Base_de_Datos'!O15<>"",'(1)_Base_de_Datos'!O15,""),"")
H121: CONTROL
H122: =IFERROR(IF('(1)_Base_de_Datos'!P15<>"",'(1)_Base_de_Datos'!P15,""),"")
B123: =IF('(1)_Base_de_Datos'!$R$16<>"",'(1)_Base_de_Datos'!$R$16,"") | H123: =IF('(1)_Base_de_Datos'!$B$16="Recomendación",'(1)_Base_de_Datos'!$B$16,"")
A124: 13 | B124: =IFERROR(IF('(1)_Base_de_Datos'!L16<>"",'(1)_Base_de_Datos'!L16,""),"") | G124: =IFERROR(IF('(1)_Base_de_Datos'!C16<>"",'(1)_Base_de_Datos'!C16,""),"") | H124: IMPLICACIÓN | L124: =IFERROR(IF('(1)_Base_de_Datos'!Q16<>"",'(1)_Base_de_Datos'!Q16,""),"") | R124: =IFERROR(IF('(1)_Base_de_Datos'!X16<>"",'(1)_Base_de_Datos'!X16,""),"") | S124: =IFERROR(IF('(1)_Base_de_Datos'!Y16<>"",'(1)_Base_de_Datos'!Y16,""),"")
B125: =IFERROR(IF('(1)_Base_de_Datos'!M16<>"",'(1)_Base_de_Datos'!M16,""),"") | H125: =IFERROR(IF('(1)_Base_de_Datos'!N16<>"",'(1)_Base_de_Datos'!N16,""),"")
H127: FUNDAMENTO
H128: =IFERROR(IF('(1)_Base_de_Datos'!O16<>"",'(1)_Base_de_Datos'!O16,""),"")
H130: CONTROL
H131: =IFERROR(IF('(1)_Base_de_Datos'!P16<>"",'(1)_Base_de_Datos'!P16,""),"")
...

Sheet Acerno_Cache_XXXXX

Sheet datos
L1: PLAN ANUAL 2025
B2: EMPRESA | D2: OBSERVACION / RECOMENDACIÓN | F2: No | G2: Riesgo | H2: Concepto | J2: CLASIFICACIÓN DE PROCESO AUDITADO | L2: NOMBRE DE LA AUDITORIA | N2: NOMBRE DEL MONITOREO | P2: CONTROL INTERNO | R2: TIPO DE HALLAZGO | T2: DEPTO DE AUDITORÍA INTERNA | V2: DEPTO DE AUDITORÍA INTERNA | W2: AUDITOR RESPONSABLE | X2: Puesto | Y2: Area del Auditor
B3: Banco BASE | D3: Observación | F3: 1 | G3: BAJO | H3: a) Observaciones sobre Actualizaciones e incumplimiento a la Normatividad Interna b) Desviaciones menores por falta de capacitación C) Inexistencia total de normatividad en procesos o actividades identificadas y realizadas por las áreas | J3: Control | L3: 31 PUNTOS BANXICO OPERACIONES DERIVADAS, MARIZ | N3: No Aplica | P3: Ausencia de Control | R3: Actualización a la Normatividad | T3: Auditoría de Tesorería y Mercados | V3: Auditoría de Tesorería y Mercados | W3: Alejandro Guadalupe Solis Arteaga | X3: Auditor Jr | Y3: TYM
B4: Casa de Bolsa BASE | D4: Recomendación | F4: 2 | G4: BAJO (Reincidente) | H4: a) Observaciones sobre Actualizaciones e incumplimiento a la Normatividad Interna b) Desviaciones menores por falta de capacitación C) Inexistencia total de normatividad en procesos o actividades identificadas y realizadas por las áreas | J4: Soporte | L4: 31 PUNTOS DE DERIVADOS | N4: Acuses de entrega de Tokens | P4: Deficiencia del diseño del control | R4: Ausencia de Normatividad | T4: Auditoría de Riesgos y Perfiles | V4: Auditoría de Riesgos y Perfiles | W4: Angela Michelle López Muñiz | X4: Auditor Jr | Y4: RYP
B5: Grupo Financiero BASE | F5: 3 | G5: MEDIO | H5: a) Observaciones relacionadas con fallas en la ejecución de Controles del proceso, sin afectaciones económicas b) Observaciones sobre Normatividad no existente o desactualizada relacionada con temas Regulatorios C) Observaciones reincidencia | J5: Negocio | L5: 31 PUNTOS DERIVADOS, MODELOS DE VALUACIÓN | N5: Actualización de atributos de garantías hipotecarias y prendarias | P5: Falla en la ejecución del control | R5: Desarrollo Tecnológico | T5: Auditoría de Operaciones Pasivas y Tecnología | V5: Auditoría de Crédito Empresarial | W5: Blanca Nelly Gutiérrez Garza | X5: Auditor Sr | Y5: CRE
F6: 4 | G6: MEDIO (Reincidente) | H6: a) Observaciones relacionadas con fallas en la ejecución de Controles del proceso, sin afectaciones económicas b) Observaciones sobre Normatividad no existente o desactualizada relacionada con temas Regulatorios C) Observaciones reincidencia | L6: ACREEDORES SALDOS NUBA | N6: Cartas de Autorización de Reporte de Buró de Crédito | R6: Diseño del Control Limitado | T6: Auditoría de Crédito Empresarial | V6: Auditoría de Operaciones Pasivas y Tecnología | W6: Brenda Nairobi Santiago Morales | X6: Auditor Jr | Y6: OPT
F7: 5 | G7: ALTO | H7: a) Observaciones sobre el incumplimientos de Controles Operativos Clave y/o Controles Automáticos sin afectaciones económicas a la Institución o cliente (No se ha materializado el Fraudes, Desviaciones o Fallas Graves de Controles, Quebrantos, etc.) b) Observaciones sobre incumplimientos regulatorios (Total o Parcial), sin antecedente de sanción aplicada a la Institución c) Observaciones relacionadas con fallas en la ejecución de Controles del proceso, con impacto económico para la Institución. d) Observaciones reincidentes | L7: ADMINISTRACION INTEGRAL DE RIESGOS (MERCADO LIQUIDEZ, CRÉDITO, OPERACIONAL) | N7: Concertación de Títulos de Terceros | R7: Falta de Capacitación | T7: Auditoría de Administración, Contabilidad y Finanzas. | V7: Auditoría de Operaciones Pasivas y Tecnología | W7: Cinthia Vianey Muro Casas | X7: Auditor Sr | Y7: OPT
F8: 6 | G8: ALTO (Reincidente) | H8: a) Observaciones sobre el incumplimientos de Controles Operativos Clave y/o Controles Automáticos sin afectaciones económicas a la Institución o cliente (No se ha materializado el Fraudes, Desviaciones o Fallas Graves de Controles, Quebrantos, etc.) b) Observaciones sobre incumplimientos regulatorios (Total o Parcial), sin antecedente de sanción aplicada a la Institución c) Observaciones relacionadas con fallas en la ejecución de Controles del proceso, con impacto económico para la Institución. d) Observaciones reincidentes | L8: ADMINISTRACIÓN Y ASIGNACIÓN DE TOKEN | N8: Confirmación de Operaciones de Productos Financieros Derivados | R8: Falta de Ejecución en el Control | V8: Auditoría de Tesorería y Mercados | W8: Diana Patricia Mosqueda Peña | X8: Auditor Jr | Y8: TYM
F9: 7 | G9: MUY ALTO | H9: a) Observaciones sobre los incumplimientos de Controles Operativos Clave y/o Controles Automáticos con afectaciones económicas a la Institución o al cliente (Fraudes, Desviaciones o Fallas Graves de Controles, Quebrantos, etc.). b) Observaciones sobre incumplimientos regulatorios (Total o Parcial), con antecedente de sanción aplicada a la Institución. c) Observaciones originadas por malas practicas que se materializaron en un riesgo a la Institución y/o clientes. d) Observaciones reincidentes cuya materialización haya tenido como consecuencia un impactado de Fraude y/o Quebranto. | L9: ALTA DESTINATARIOS | N9: Contratos Márgenes Únicos | R9: Inexistencia de Control | V9: Auditoría de Tesorería y Mercados | W9: Domingo José Palermo Rodríguez | X9: Subdirector de Auditoría | Y9: TYM
F10: 8 | G10: MUY ALTO (Reincidente) | H10: a) Observaciones sobre los incumplimientos de Controles Operativos Clave y/o Controles Automáticos con afectaciones económicas a la Institución o al cliente (Fraudes, Desviaciones o Fallas Graves de Controles, Quebrantos, etc.). b) Observaciones sobre incumplimientos regulatorios (Total o Parcial), con antecedente de sanción aplicada a la Institución. c) Observaciones originadas por malas practicas que se materializaron en un riesgo a la Institución y/o clientes. d) Observaciones reincidentes cuya materialización haya tenido como consecuencia un impactado de Fraude y/o Quebranto. | L10: ALTAS, BAJAS Y CAMBIOS DE USUARIOS | N10: Cuentas de Clientes con depósitos de Colaboradores | R10: Incumplimiento Regulatorio | V10: Auditoría de Riesgos y Perfiles | W10: Elias Escobedo García | X10: Auditor Sr | Y10: RYP
L11: APLICACIONES DE NEGOCIO | N11: Cuestionario de Gobierno Corporativo | V11: Auditoría de Riesgos y Perfiles | W11: Erick Alberto Merinos García | X11: Auditor Sr | Y11: RYP
L12: ARQUEOS DE CAJA | N12: Custodia de Documentos Originales de Captación | V12: Auditoría de Crédito Empresarial | W12: Evelyn Natividad Gochar Calderón | X12: Auditor Jr | Y12: CRE
L13: ARRENDAMIENTO MEXICO | N13: Diario de Revelación del CCL | V13: Auditoría de Riesgos y Perfiles | W13: Evelyn Yamileth Martínez Galván | X13: Auditor Jr | Y13: RYP
L14: ARRENDAMIENTO MONTERREY | N14: Efectivo en cajas al final del día | V14: Auditoría de Operaciones Pasivas y Tecnología | W14: Fernando Huerta López | X14: Gerente de Auditoría | Y14: OPT
L15: AUDITORIA LEGAL | N15: Eliminación de Cuentas de Usuarios en el Directorio Activo | V15: Auditoría de Operaciones Pasivas y Tecnología | W15: Griselda Torres Martínez | X15: Auditor Sr | Y15: OPT
L16: BANCA ELECTRONICA | N16: Empleados en periodos de inactividad vacaciones o incapacidades | V16: Auditoría de Tesorería y Mercados | W16: Jorge Alberto Maldonado Cantú | X16: Auditor Sr | Y16: TYM
L17: BIENES ADJUNDICADOS | N17: Liquidación de Operaciones en cuentas autorizadas de contratos de Mercado de Dinero | V17: Auditoría de Operaciones Pasivas y Tecnología | W17: Jorge Ugarte Muro | X17: Auditor Sr | Y17: OPT
L18: BIOMETRICOS Y ROBO DE IDENTIDAD | N18: Liquidación de Operaciones en cuentas autorizadas de contratos de Mercado de Dinero, Capitales y Fondos de Inversión | V18: Auditoría de Riesgos y Perfiles | W18: José Enrique Duque Leal | X18: Gerente de Auditoría | Y18: RYP
L19: BLOQUEO Y RESTRICCIÓN CLIENTES POR OFICIOS | N19: Mensual Cuotas IPAB | V19: Auditoría de Operaciones Pasivas y Tecnología | W19: Julio Manuel Flores Treviño | X19: Auditor Sr | Y19: OPT
L20: BURO DE CREDITO - ADMINISTRACIÓN EXPEDIENTES | N20: Págares (Banco y Arrendadora) | V20: Auditoría de Operaciones Pasivas y Tecnología | W20: Oscar Montelongo Vázquez | X20: Auditor Sr | Y20: OPT
L21: BURÓ DE CRÉDITO - REPORTE A BURÓ DE CRÉDITO | N21: Pólizas Manuales | V21: Auditoría de Crédito Empresarial | W21: Rafael Pacheco Torres | X21: Gerente de Auditoría | Y21: CRE
L22: CAJAS OPERATIVAS Y OPERACIONES EN EFECTIVO | N22: Recalificación de Líneas de Crédito | V22: Auditoría de Operaciones Pasivas y Tecnología | W22: Samantha Kahori Cobarrubias Ubaldo | X22: Analista Auditoría TI | Y22: OPT
L23: CALIDAD DE INFORMACIÓN DE CLIENTES | N23: Recalificación de Líneas de Derivados | V23: Auditoría de Riesgos y Perfiles | W23: Yarelli Michell Cruz Sánchez | X23: Auditor Jr | Y23: RYP
L24: CALIFICACION DE CARTERA | N24: Retiro de Efectivo Empleados
L25: CAMBIOS | N25: Segregación de funciones
L26: CARTAS DE CRÉDITO | N26: Solicitudes de Financiamiento, Visitas Oculares, Avalúos y Pólizas de Seguro
L27: CCL - CFEN | N27: Validación de datos de proveedores de la Institución (Minería de Datos)
L28: CENTRO DE ACLARACION Y SERVICIO CAS | N28: Validación de listado de proveedores críticos con base en los Anexos 69 y 69B del CFF
L29: CERTIFICA CIONES CNBV USO HERRAMIENTAS INFORMÁTICAS PREV DE FRAUDES | N29: Verificación de Reportes de Aclaraciones, Consultas y Reclamaciones en UNE
L30: CERTIFICACIÓN ANUAL CUOTAS IPAB
L31: CERTIFICACION PARTES RELACIONADAS
L32: CERTIFICACION REPORTES REGULATORIOS
L33: CERTIFICACIÓN SPEI Externo
L34: CERTIFICACIÓN SWIFT
L35: CERTIFICACIONES CNBV CONTRASEÑAS Bca x Int Web y Movil
L36: CERTIFICACIONES CNBV NOTIFICACIONES Art 51
L37: CERTIFICACIONES CNBV SOFT TOKEN
L38: CERTIFICACIONES CNBV TIEMPOS ESPERA TRANSF. TERCEROS BASEINET
L39: CFEN
L40: CHEQUERA DIGITAL - CAPTACIÓN A LA VISTA
L41: COEFICIENTE DE COBERTURA DE LIQUIDEZ CCL
... L173: VARIACIONES FINANCIERAS Y REPORTE A AUTORIDADES

Sheet Plantilla
A2: INFORMACION AGOSTO 2026
B3: 1 | C3: 2 | D3: 3 | E3: 4 | F3: 5 | G3: 6 | H3: 7 | I3: 8 | J3: 9 | K3: 10 | L3: 11 | M3: 12 | N3: 13 | O3: 14 | P3: 15 | Q3: 16 | R3: 17 | S3: 18 | T3: 19 | U3: 20 | V3: 21 | W3: 22 | X3: 23 | Y3: 24 | Z3: 25 | AA3: 26 | AB3: 27 | AC3: 28 | AD3: 29 | AE3: 30 | AF3: 31 | AG3: 32 | AH3: 33 | AI3: 34 | AJ3: 35
A4: USUARIO | B4: NIP | C4: NOMBRE | D4: CODIGO POSICION | E4: POSICION | F4: ATRIBUTO SUCURSAL | G4: NIP DEL JEFE | H4: NOMBRE DEL JEFE | I4: CODIGO POSICION DEL JEFE | J4: POSICION DEL JEFE | K4: ID ELEMENTO EMPRESA | L4: DESCRIPCION EMPRESA | M4: ID ELEMENTO DIRECCION GENERAL | N4: DESCRIPCION DIRECCION GENERAL | O4: ID ELEMENTO DIRECCION | P4: DESCRIPCION DIRECCION | Q4: ID ELEMENTO AREA | R4: DESCRIPCION AREA | S4: ID ELEMENTO GERENCIA | T4: DESCRIPCION GERENCIA | U4: ID ELEMENTO DEPARTAMENTO CC | V4: DESCRIPCION DEPARTAMENTO CC | W4: ID ELEMENTO CENTRO DE RESP | X4: DESCRIPCION CENTRO DE RESP | Y4: CLAVE ETIQUETA 1 | Z4: DESCRIPCION ETIQUETA 1 | AA4: CLAVE ETIQUETA 2 | AB4: DESCRIPCION ETIQUETA 2 | AC4: CLAVE ETIQUETA 3 | AD4: DESCRIPCION ETIQUETA 3 | AE4: CLAVE ETIQUETA 4 | AF4: DESCRIPCION ETIQUETA 4 | AG4: ID ELEMENTO PLAZA | AH4: DESCRIPCION PLAZA | AI4: Correo Electrónico | AJ4: Fecha Ingreso
A5: LBARRERA | B5: 1 | C5: LORENZO BARRERA SEGOVIA | D5: 1 | E5: PRESIDENTE EJECUTIVO | F5: MONTERREY | K5: 1 | L5: PRESIDENCIA EJECUTIVA DEL CONSEJO | M5: 10 | N5: PRESIDENCIA EJECUTIVA DEL CONSEJO | O5: 100 | P5: PRESIDENCIA DEL CONSEJO DE ADMINISTRACION | Q5: 1000 | R5: PRESIDENCIA DEL CONSEJO DE ADMINISTRACION | S5: 10000 | T5: PRESIDENCIA DEL CONSEJO DE ADMINISTRACION | U5: 100000 | V5: PRESIDENCIA DEL CONSEJO DE ADMINISTRACION | W5: 100101 | X5: CORPORATIVO | Y5: 4 | Z5: CORPORATIVO | AA5: 1 | AB5: NEGOCIO EN MARCHA | AC5: 1 | AD5: BANCO | AE5: 1 | AF5: BACK | AG5: 100101 | AH5: CORPORATIVO | AI5: LBARRERA@BANCOBASE.COM | AJ5: 31444
A6: DLOZA | B6: 604 | C6: DIANA LOZA ALVAREZ | D6: 191 | E6: ASISTENTE DE PRESIDENCIA | F6: MONTERREY | G6: 1 | H6: LORENZO BARRERA SEGOVIA | I6: 1 | J6: PRESIDENTE EJECUTIVO | K6: 1 | L6: PRESIDENCIA EJECUTIVA DEL CONSEJO | M6: 10 | N6: PRESIDENCIA EJECUTIVA DEL CONSEJO | O6: 100 | P6: PRESIDENCIA DEL CONSEJO DE ADMINISTRACION | Q6: 1000 | R6: PRESIDENCIA DEL CONSEJO DE ADMINISTRACION | S6: 10000 | T6: PRESIDENCIA DEL CONSEJO DE ADMINISTRACION | U6: 100000 | V6: PRESIDENCIA DEL CONSEJO DE ADMINISTRACION | W6: 100101 | X6: CORPORATIVO | Y6: 4 | Z6: CORPORATIVO | AA6: 1 | AB6: NEGOCIO EN MARCHA | AC6: 1 | AD6: BANCO | AE6: 1 | AF6: BACK | AG6: 100101 | AH6: CORPORATIVO | AI6: DLOZA@BANCOBASE.COM | AJ6: 40273
A7: LARRAMBIDE | B7: 856 | C7: LIZETH ARRAMBIDE ORTIZ | D7: 9130 | E7: ASISTENTE DE PRESIDENCIA | F7: MONTERREY | G7: 1 | H7: LORENZO BARRERA SEGOVIA | I7: 1 | J7: PRESIDENTE EJECUTIVO | K7: 1 | L7: PRESIDENCIA EJECUTIVA DEL CONSEJO | M7: 10 | N7: PRESIDENCIA EJECUTIVA DEL CONSEJO | O7: 100 | P7: PRESIDENCIA DEL CONSEJO DE ADMINISTRACION | Q7: 1000 | R7: PRESIDENCIA DEL CONSEJO DE ADMINISTRACION | S7: 10000 | T7: PRESIDENCIA DEL CONSEJO DE ADMINISTRACION | U7: 100000 | V7: PRESIDENCIA DEL CONSEJO DE ADMINISTRACION | W7: 100101 | X7: CORPORATIVO | Y7: 4 | Z7: CORPORATIVO | AA7: 1 | AB7: NEGOCIO EN MARCHA | AC7: 1 | AD7: BANCO | AE7: 1 | AF7: BACK | AG7: 100101 | AH7: CORPORATIVO | AI7: LARRAMBIDE@BANCOBASE.COM | AJ7: 44186
A8: VCASTILLO | B8: 237 | C8: VICTOR MANUEL CASTILLO TAMEZ | D8: 9449 | E8: CHOFER | F8: MONTERREY | G8: 1 | H8: LORENZO BARRERA SEGOVIA | I8: 1 | J8: PRESIDENTE EJECUTIVO | K8: 1 | L8: PRESIDENCIA EJECUTIVA DEL CONSEJO | M8: 10 | N8: PRESIDENCIA EJECUTIVA DEL CONSEJO | O8: 100 | P8: PRESIDENCIA DEL CONSEJO DE ADMINISTRACION | Q8: 1000 | R8: PRESIDENCIA DEL CONSEJO DE ADMINISTRACION | S8: 10000 | T8: PRESIDENCIA DEL CONSEJO DE ADMINISTRACION | U8: 100000 | V8: PRESIDENCIA DEL CONSEJO DE ADMINISTRACION | W8: 100101 | X8: CORPORATIVO | Y8: 4 | Z8: CORPORATIVO | AA8: 1 | AB8: NEGOCIO EN MARCHA | AC8: 1 | AD8: BANCO | AE8: 1 | AF8: BACK | AG8: 100101 | AH8: CORPORATIVO | AI8: VCASTILLO@BANCOBASE.COM | AJ8: 37849
A9: ABARRERA | B9: 2 | C9: ALVARO BARRERA SEGOVIA | D9: 3 | E9: VICEPRESIDENTE DEL CONSEJO DE ADMINISTRACION | F9: MONTERREY | G9: 1 | H9: LORENZO BARRERA SEGOVIA | I9: 1 | J9: PRESIDENTE EJECUTIVO | K9: 1 | L9: PRESIDENCIA EJECUTIVA DEL CONSEJO | M9: 20 | N9: VICEPRESIDENCIA DEL CONSEJO DE ADMINISTRACION | O9: 200 | P9: VICEPRESIDENCIA DEL CONSEJO DE ADMINISTRACION | Q9: 2000 | R9: VICEPRESIDENCIA DEL CONSEJO DE ADMINISTRACION | S9: 20000 | T9: VICEPRESIDENCIA DEL CONSEJO DE ADMINISTRACION | U9: 200000 | V9: VICEPRESIDENCIA DEL CONSEJO DE ADMINISTRACION | W9: 100101 | X9: CORPORATIVO | Y9: 4 | Z9: CORPORATIVO | AA9: 1 | AB9: NEGOCIO EN MARCHA | AC9: 1 | AD9: BANCO | AE9: 1 | AF9: BACK | AG9: 100101 | AH9: CORPORATIVO | AI9: ABARRERA@BANCOBASE.COM | AJ9: 31625
A10: AVILLARREA | B10: 509 | C10: ALEJANDRA VILLARREAL MORALES | D10: 5393 | E10: ASISTENTE DE VICEPRESIDENCIA | F10: MONTERREY | G10: 2 | H10: ALVARO BARRERA SEGOVIA | I10: 3 | J10: VICEPRESIDENTE DEL CONSEJO DE ADMINISTRACION | K10: 1 | L10: PRESIDENCIA EJECUTIVA DEL CONSEJO | M10: 20 | N10: VICEPRESIDENCIA DEL CONSEJO DE ADMINISTRACION | O10: 200 | P10: VICEPRESIDENCIA DEL CONSEJO DE ADMINISTRACION | Q10: 2000 | R10: VICEPRESIDENCIA DEL CONSEJO DE ADMINISTRACION | S10: 20000 | T10: VICEPRESIDENCIA DEL CONSEJO DE ADMINISTRACION | U10: 200000 | V10: VICEPRESIDENCIA DEL CONSEJO DE ADMINISTRACION | W10: 100101 | X10: CORPORATIVO | Y10: 4 | Z10: CORPORATIVO | AA10: 1 | AB10: NEGOCIO EN MARCHA | AC10: 1 | AD10: BANCO | AE10: 1 | AF10: BACK | AG10: 100101 | AH10: CORPORATIVO | AI10: AVILLARREA@BANCOBASE.COM | AJ10: 39696
A11: OPEREZC | B11: 99526 | C11: ORLANDO PATRICIO PEREZ CARDENAS | D11: 7009 | E11: PRACTICANTE | F11: MONTERREY | G11: 509 | H11: ALEJANDRA VILLARREAL MORALES | I11: 5393 | J11: ASISTENTE DE VICEPRESIDENCIA | K11: 1 | L11: PRESIDENCIA EJECUTIVA DEL CONSEJO | M11: 20 | N11: VICEPRESIDENCIA DEL CONSEJO DE ADMINISTRACION | O11: 200 | P11: VICEPRESIDENCIA DEL CONSEJO DE ADMINISTRACION | Q11: 2000 | R11: VICEPRESIDENCIA DEL CONSEJO DE ADMINISTRACION | S11: 20000 | T11: VICEPRESIDENCIA DEL CONSEJO DE ADMINISTRACION | U11: 200000 | V11: VICEPRESIDENCIA DEL CONSEJO DE ADMINISTRACION | W11: 100101 | X11: CORPORATIVO | Y11: 4 | Z11: CORPORATIVO | AA11: 1 | AB11: NEGOCIO EN MARCHA | AC11: 1 | AD11: BANCO | AE11: 1 | AF11: BACK | AG11: 100101 | AH11: CORPORATIVO | AI11: OPEREZC@BANCOBASE.COM | AJ11: 46041
A12: RTOBIAS | B12: 750 | C12: RODRIGO TOBIAS CASTILLEJA | D12: 10296 | E12: CHOFER | F12: MONTERREY | G12: 2 | H12: ALVARO BARRERA SEGOVIA | I12: 3 | J12: VICEPRESIDENTE DEL CONSEJO DE ADMINISTRACION | K12: 1 | L12: PRESIDENCIA EJECUTIVA DEL CONSEJO | M12: 20 | N12: VICEPRESIDENCIA DEL CONSEJO DE ADMINISTRACION | O12: 200 | P12: VICEPRESIDENCIA DEL CONSEJO DE ADMINISTRACION | Q12: 2000 | R12: VICEPRESIDENCIA DEL CONSEJO DE ADMINISTRACION | S12: 20000 | T12: VICEPRESIDENCIA DEL CONSEJO DE ADMINISTRACION | U12: 200000 | V12: VICEPRESIDENCIA DEL CONSEJO DE ADMINISTRACION | W12: 100101 | X12: CORPORATIVO | Y12: 4 | Z12: CORPORATIVO | AA12: 1 | AB12: NEGOCIO EN MARCHA | AC12: 1 | AD12: BANCO | AE12: 1 | AF12: BACK | AG12: 100101 | AH12: CORPORATIVO | AI12: RTOBIAS@BANCOBASE.COM | AJ12: 40710
A13: OFELIX | B13: 172 | C13: OMAR PAUL FELIX BOJORQUEZ | D13: 9518 | E13: ESPECIALISTA DE GESTION | F13: MONTERREY | G13: 2 | H13: ALVARO BARRERA SEGOVIA | I13: 3 | J13: VICEPRESIDENTE DEL CONSEJO DE ADMINISTRACION | K13: 1 | L13: PRESIDENCIA EJECUTIVA DEL CONSEJO | M13: 20 | N13: VICEPRESIDENCIA DEL CONSEJO DE ADMINISTRACION | O13: 200 | P13: VICEPRESIDENCIA DEL CONSEJO DE ADMINISTRACION | Q13: 2000 | R13: VICEPRESIDENCIA DEL CONSEJO DE ADMINISTRACION | S13: 20000 | T13: VICEPRESIDENCIA DEL CONSEJO DE ADMINISTRACION | U13: 200000 | V13: VICEPRESIDENCIA DEL CONSEJO DE ADMINISTRACION | W13: 100101 | X13: CORPORATIVO | Y13: 4 | Z13: CORPORATIVO | AA13: 1 | AB13: NEGOCIO EN MARCHA | AC13: 1 | AD13: BANCO | AE13: 1 | AF13: BACK | AG13: 100101 | AH13: CORPORATIVO | AI13: OFELIX@BANCOBASE.COM | AJ13: 36846
A14: JESCANDON | B14: 386 | C14: JULIO RICARDO ESCANDON JIMENEZ | D14: 10324 | E14: DIRECTOR GENERAL | F14: MONTERREY | G14: 1 | H14: LORENZO BARRERA SEGOVIA | I14: 1 | J14: PRESIDENTE EJECUTIVO | K14: 1 | L14: PRESIDENCIA EJECUTIVA DEL CONSEJO | M14: 40 | N14: DIRECCION GENERAL BANCO BASE | O14: 400 | P14: DIRECCION GENERAL | Q14: 4000 | R14: DIRECCION GENERAL | S14: 40000 | T14: DIRECCION GENERAL | U14: 400000 | V14: DIRECCION GENERAL | W14: 100101 | X14: CORPORATIVO | Y14: 4 | Z14: CORPORATIVO | AA14: 1 | AB14: NEGOCIO EN MARCHA | AC14: 1 | AD14: BANCO | AE14: 1 | AF14: BACK | AG14: 100101 | AH14: CORPORATIVO | AI14: JESCANDON@BANCOBASE.COM | AJ14: 39114
A15: NYANEZ | B15: 3737 | C15: NANCY YANEZ ANAYA | D15: 194 | E15: ASISTENTE DE DIRECCION GENERAL | F15: MONTERREY | G15: 386 | H15: JULIO RICARDO ESCANDON JIMENEZ | I15: 10324 | J15: DIRECTOR GENERAL | K15: 1 | L15: PRESIDENCIA EJECUTIVA DEL CONSEJO | M15: 40 | N15: DIRECCION GENERAL BANCO BASE | O15: 400 | P15: DIRECCION GENERAL | Q15: 4000 | R15: DIRECCION GENERAL | S15: 40000 | T15: DIRECCION GENERAL | U15: 400000 | V15: DIRECCION GENERAL | W15: 100101 | X15: CORPORATIVO | Y15: 4 | Z15: CORPORATIVO | AA15: 1 | AB15: NEGOCIO EN MARCHA | AC15: 1 | AD15: BANCO | AE15: 1 | AF15: BACK | AG15: 100101 | AH15: CORPORATIVO | AI15: NYANEZ@BANCOBASE.COM | AJ15: 46031
A16: LBARRERAJ | B16: 1694 | C16: LORENZO BARRERA JAIME | D16: 9953 | E16: DIRECTOR GENERAL ADJUNTO DE PRODUCTO Y TRANSFORMACION | F16: MONTERREY | G16: 386 | H16: JULIO RICARDO ESCANDON JIMENEZ | I16: 10324 | J16: DIRECTOR GENERAL | K16: 1 | L16: PRESIDENCIA EJECUTIVA DEL CONSEJO | M16: 30 | N16: DIRECCION GENERAL ADJUNTA PRODUCTO Y TRANSFORMACIO | O16: 300 | P16: DIRECCION GENERAL ADJUNTA PRODUCTO Y TRANSFORMACIO | Q16: 3000 | R16: DIRECCION GENERAL ADJUNTA PRODUCTO Y TRANSFORMACIO | S16: 30000 | T16: DIRECCION GENERAL ADJUNTA PRODUCTO Y TRANSFORMACIO | U16: 300000 | V16: DIRECCION GENERAL ADJUNTA PRODUCTO Y TRANSFORMACIO | W16: 100101 | X16: CORPORATIVO | Y16: 4 | Z16: CORPORATIVO | AA16: 1 | AB16: NEGOCIO EN MARCHA | AC16: 1 | AD16: BANCO | AE16: 1 | AF16: BACK | AG16: 100101 | AH16: CORPORATIVO | AI16: LBARRERAJ@BANCOBASE.COM | AJ16: 42755
A17: GMARTINEZS | B17: 3165 | C17: GLORIA MARIBEL MARTINEZ SEPULVEDA | D17: 10397 | E17: ASISTENTE DE DIRECCION | F17: MONTERREY | G17: 1694 | H17: LORENZO BARRERA JAIME | I17: 9953 | J17: DIRECTOR GENERAL ADJUNTO DE PRODUCTO Y TRANSFORMACION | K17: 1 | L17: PRESIDENCIA EJECUTIVA DEL CONSEJO | M17: 30 | N17: DIRECCION GENERAL ADJUNTA PRODUCTO Y TRANSFORMACIO | O17: 300 | P17: DIRECCION GENERAL ADJUNTA PRODUCTO Y TRANSFORMACIO | Q17: 3000 | R17: DIRECCION GENERAL ADJUNTA PRODUCTO Y TRANSFORMACIO | S17: 30000 | T17: DIRECCION GENERAL ADJUNTA PRODUCTO Y TRANSFORMACIO | U17: 300000 | V17: DIRECCION GENERAL ADJUNTA PRODUCTO Y TRANSFORMACIO | W17: 100101 | X17: CORPORATIVO | Y17: 4 | Z17: CORPORATIVO | AA17: 1 | AB17: NEGOCIO EN MARCHA | AC17: 1 | AD17: BANCO | AE17: 1 | AF17: BACK | AG17: 100101 | AH17: CORPORATIVO | AI17: GMARTINEZS@BANCOBASE.COM | AJ17: 45489
... A68: BVAZQUEZM | B68: 3961 | C68: BELINDA VAZQUEZ MADRIGAL | D68: 9123 | E68: ANALISTA DE SOPORTE ADMINISTRATIVO | F68: MONTERREY | G68: 3162 | H68: MONTSERRAT LOPEZ GARCIA | I68: 5077 | J68: COORDINADOR DE ABASTECIMIENTOS | K68: 1 | L68: PRESIDENCIA EJECUTIVA DEL CONSEJO | M68: 40 | N68: DIRECCION GENERAL BANCO BASE | O68: 420 | P68: DIRECCION ADMINISTRACION Y FINANZAS | Q68: 4220 | R68: DIRECCION DE ADMINISTRACION | S68: 42240 | T68: SUBDIRECCION DE COMPRAS Y HABILITACION DE ESPACIOS | U68: 422316 | V68: GERENCIA CONTROL DE GASTOS Y ABASTECIMIENTO | W68: 100101 | X68: CORPORATIVO | Y68: 4 | Z68: CORPORATIVO | AA68: 1 | AB68: NEGOCIO EN MARCHA | AC68: 1 | AD68: BANCO | AE68: 1 | AF68: BACK | AG68: 100101 | AH68: CORPORATIVO | AI68: BVAZQUEZM@BANCOBASE.COM | AJ68: 46237
A69: ACRUZY | B69: 2977 | C69: LUIS ALEJANDRO DE LA CRUZ YAÑEZ | D69: 9626 | E69: AUXILIAR DE SEGURIDAD | F69: MONTERREY | I69: 9010 | J69: COORDINADOR DE SEGURIDAD | K69: 1 | L69: PRESIDENCIA EJECUTIVA DEL CONSEJO | M69: 40 | N69: DIRECCION GENERAL BANCO BASE | O69: 420 | P69: DIRECCION ADMINISTRACION Y FINANZAS | Q69: 4220 | R69: DIRECCION DE ADMINISTRACION | S69: 42240 | T69: SUBDIRECCION DE COMPRAS Y HABILITACION DE ESPACIOS | U69: 422320 | V69: SEGURIDAD CORPORATIVA | W69: 100101 | X69: CORPORATIVO | Y69: 4 | Z69: CORPORATIVO | AA69: 1 | AB69: NEGOCIO EN MARCHA | AC69: 1 | AD69: BANCO | AE69: 1 | AF69: BACK | AG69: 100101 | AH69: CORPORATIVO | AI69: ACRUZY@BANCOBASE.COM | AJ69: 45231
A70: AGALLEGOS | B70: 756 | C70: AMELIA GALLEGOS GALVAN | D70: 47 | E70: GERENTE DE CONTABILIDAD | F70: MONTERREY | G70: 209 | H70: ROBERTO MUÑOZ SALAZAR | I70: 9463 | J70: DIRECTOR DE ADMINISTRACION | K70: 1 | L70: PRESIDENCIA EJECUTIVA DEL CONSEJO | M70: 40 | N70: DIRECCION GENERAL BANCO BASE | O70: 420 | P70: DIRECCION ADMINISTRACION Y FINANZAS | Q70: 4220 | R70: DIRECCION DE ADMINISTRACION | S70: 42210 | T70: GERENCIA DE CONTABILIDAD | U70: 422101 | V70: CONTABILIDAD | W70: 100101 | X70: CORPORATIVO | Y70: 4 | Z70: CORPORATIVO | AA70: 1 | AB70: NEGOCIO EN MARCHA | AC70: 1 | AD70: BANCO | AE70: 1 | AF70: BACK | AG70: 100101 | AH70: CORPORATIVO | AI70: AGALLEGOS@BANCOBASE.COM | AJ70: 40725
A71: AHERNANDES | B71: 1056 | C71: ARACELI HERNANDEZ SANCHEZ | D71: 8384 | E71: COORDINADOR DE CONTABILIDAD | F71: MONTERREY | G71: 756 | H71: AMELIA GALLEGOS GALVAN | I71: 47 | J71: GERENTE DE CONTABILIDAD | K71: 1 | L71: PRESIDENCIA EJECUTIVA DEL CONSEJO | M71: 40 | N71: DIRECCION GENERAL BANCO BASE | O71: 420 | P71: DIRECCION ADMINISTRACION Y FINANZAS | Q71: 4220 | R71: DIRECCION DE ADMINISTRACION | S71: 42210 | T71: GERENCIA DE CONTABILIDAD | U71: 422101 | V71: CONTABILIDAD | W71: 100101 | X71: CORPORATIVO | Y71: 4 | Z71: CORPORATIVO | AA71: 1 | AB71: NEGOCIO EN MARCHA | AC71: 1 | AD71: BANCO | AE71: 1 | AF71: BACK | AG71: 100101 | AH71: CORPORATIVO | AI71: AHERNANDES@BANCOBASE.COM | AJ71: 41502
A72: ASALINASV | B72: 3006 | C72: ALONDRA MONSERRAT SALINAS VARGAS | D72: 8275 | E72: ANALISTA CONTABLE | F72: MONTERREY | G72: 1056 | H72: ARACELI HERNANDEZ SANCHEZ | I72: 8384 | J72: COORDINADOR DE CONTABILIDAD | K72: 1 | L72: PRESIDENCIA EJECUTIVA DEL CONSEJO | M72: 40 | N72: DIRECCION GENERAL BANCO BASE | O72: 420 | P72: DIRECCION ADMINISTRACION Y FINANZAS | Q72: 4220 | R72: DIRECCION DE ADMINISTRACION | S72: 42210 | T72: GERENCIA DE CONTABILIDAD | U72: 422101 | V72: CONTABILIDAD | W72: 100101 | X72: CORPORATIVO | Y72: 4 | Z72: CORPORATIVO | AA72: 1 | AB72: NEGOCIO EN MARCHA | AC72: 1 | AD72: BANCO | AE72: 1 | AF72: BACK | AG72: 100101 | AH72: CORPORATIVO | AI72: ASALINASV@BANCOBASE.COM | AJ72: 45293
A73: EPENA | B73: 2074 | C73: CYNTHIA ESTHELA PEÑA MARTINEZ | D73: 8385 | E73: COORDINADOR DE CONTABILIDAD | F73: MONTERREY | G73: 756 | H73: AMELIA GALLEGOS GALVAN | I73: 47 | J73: GERENTE DE CONTABILIDAD | K73: 1 | L73: PRESIDENCIA EJECUTIVA DEL CONSEJO | M73: 40 | N73: DIRECCION GENERAL BANCO BASE | O73: 420 | P73: DIRECCION ADMINISTRACION Y FINANZAS | Q73: 4220 | R73: DIRECCION DE ADMINISTRACION | S73: 42210 | T73: GERENCIA DE CONTABILIDAD | U73: 422101 | V73: CONTABILIDAD | W73: 100101 | X73: CORPORATIVO | Y73: 4 | Z73: CORPORATIVO | AA73: 1 | AB73: NEGOCIO EN MARCHA | AC73: 1 | AD73: BANCO | AE73: 1 | AF73: BACK | AG73: 100101 | AH73: CORPORATIVO | AI73: EPENA@BANCOBASE.COM | AJ73: 43328
A74: ACANO | B74: 2884 | C74: AXEL JOAN CANO ESPINOZA | D74: 8134 | E74: ANALISTA CONTABLE | F74: MONTERREY | G74: 2074 | H74: CYNTHIA ESTHELA PEÑA MARTINEZ | I74: 8385 | J74: COORDINADOR DE CONTABILIDAD | K74: 1 | L74: PRESIDENCIA EJECUTIVA DEL CONSEJO | M74: 40 | N74: DIRECCION GENERAL BANCO BASE | O74: 420 | P74: DIRECCION ADMINISTRACION Y FINANZAS | Q74: 4220 | R74: DIRECCION DE ADMINISTRACION | S74: 42210 | T74: GERENCIA DE CONTABILIDAD | U74: 422101 | V74: CONTABILIDAD | W74: 100101 | X74: CORPORATIVO | Y74: 4 | Z74: CORPORATIVO | AA74: 1 | AB74: NEGOCIO EN MARCHA | AC74: 1 | AD74: BANCO | AE74: 1 | AF74: BACK | AG74: 100101 | AH74: CORPORATIVO | AI74: ACANO@BANCOBASE.COM | AJ74: 45047
A75: MRAMIREZM | B75: 1941 | C75: MAGDA LIDIA RAMIREZ MARTINEZ | D75: 8230 | E75: COORDINADOR DE CUENTAS POR PAGAR | F75: MONTERREY | G75: 756 | H75: AMELIA GALLEGOS GALVAN | I75: 47 | J75: GERENTE DE CONTABILIDAD | K75: 1 | L75: PRESIDENCIA EJECUTIVA DEL CONSEJO | M75: 40 | N75: DIRECCION GENERAL BANCO BASE | O75: 420 | P75: DIRECCION ADMINISTRACION Y FINANZAS | Q75: 4220 | R75: DIRECCION DE ADMINISTRACION | S75: 42210 | T75: GERENCIA DE CONTABILIDAD | U75: 422101 | V75: CONTABILIDAD | W75: 100101 | X75: CORPORATIVO | Y75: 4 | Z75: CORPORATIVO | AA75: 1 | AB75: NEGOCIO EN MARCHA | AC75: 1 | AD75: BANCO | AE75: 1 | AF75: BACK | AG75: 100101 | AH75: CORPORATIVO | AI75: MRAMIREZM@BANCOBASE.COM | AJ75: 43147
A76: QLEIJA | B76: 3949 | C76: QUETZALY GUADALUPE LEIJA VILLALOBOS | D76: 9017 | E76: ANALISTA CUENTAS POR PAGAR | F76: MONTERREY | G76: 1941 | H76: MAGDA LIDIA RAMIREZ MARTINEZ | I76: 8230 | J76: COORDINADOR DE CUENTAS POR PAGAR | K76: 1 | L76: PRESIDENCIA EJECUTIVA DEL CONSEJO | M76: 40 | N76: DIRECCION GENERAL BANCO BASE | O76: 420 | P76: DIRECCION ADMINISTRACION Y FINANZAS | Q76: 4220 | R76: DIRECCION DE ADMINISTRACION | S76: 42210 | T76: GERENCIA DE CONTABILIDAD | U76: 422101 | V76: CONTABILIDAD | W76: 100101 | X76: CORPORATIVO | Y76: 4 | Z76: CORPORATIVO | AA76: 1 | AB76: NEGOCIO EN MARCHA | AC76: 1 | AD76: BANCO | AE76: 1 | AF76: BACK | AG76: 100101 | AH76: CORPORATIVO | AI76: QLEIJA@BANCOBASE.COM | AJ76: 46219
A77: VARMENDAR | B77: 3220 | C77: VALERIA SALOME ARMENDARIZ RAMIREZ | D77: 10423 | E77: ANALISTA CUENTAS POR PAGAR | F77: MONTERREY | G77: 1941 | H77: MAGDA LIDIA RAMIREZ MARTINEZ | I77: 8230 | J77: COORDINADOR DE CUENTAS POR PAGAR | K77: 1 | L77: PRESIDENCIA EJECUTIVA DEL CONSEJO | M77: 40 | N77: DIRECCION GENERAL BANCO BASE | O77: 420 | P77: DIRECCION ADMINISTRACION Y FINANZAS | Q77: 4220 | R77: DIRECCION DE ADMINISTRACION | S77: 42210 | T77: GERENCIA DE CONTABILIDAD | U77: 422101 | V77: CONTABILIDAD | W77: 100101 | X77: CORPORATIVO | Y77: 4 | Z77: CORPORATIVO | AA77: 1 | AB77: NEGOCIO EN MARCHA | AC77: 1 | AD77: BANCO | AE77: 1 | AF77: BACK | AG77: 100101 | AH77: CORPORATIVO | AI77: VARMENDAR@BANCOBASE.COM | AJ77: 45572
A78: JLARAR | B78: 2997 | C78: JAIME ALEJANDRO LARA ROJAS | D78: 8270 | E78: ESPECIALISTA DE CONTABILIDAD | F78: MONTERREY | G78: 756 | H78: AMELIA GALLEGOS GALVAN | I78: 47 | J78: GERENTE DE CONTABILIDAD | K78: 1 | L78: PRESIDENCIA EJECUTIVA DEL CONSEJO | M78: 40 | N78: DIRECCION GENERAL BANCO BASE | O78: 420 | P78: DIRECCION ADMINISTRACION Y FINANZAS | Q78: 4220 | R78: DIRECCION DE ADMINISTRACION | S78: 42210 | T78: GERENCIA DE CONTABILIDAD | U78: 422101 | V78: CONTABILIDAD | W78: 100101 | X78: CORPORATIVO | Y78: 4 | Z78: CORPORATIVO | AA78: 1 | AB78: NEGOCIO EN MARCHA | AC78: 1 | AD78: BANCO | AE78: 1 | AF78: BACK | AG78: 100101 | AH78: CORPORATIVO | AI78: JLARAR@BANCOBASE.COM | AJ78: 45261
A79: MPEREZR | B79: 713 | C79: MONICA GABRIELA PEREZ RAMIREZ | D79: 10026 | E79: GERENTE ADMINISTRATIVO | F79: MEXICO | G79: 209 | H79: ROBERTO MUÑOZ SALAZAR | I79: 9463 | J79: DIRECTOR DE ADMINISTRACION | K79: 1 | L79: PRESIDENCIA EJECUTIVA DEL CONSEJO | M79: 40 | N79: DIRECCION GENERAL BANCO BASE | O79: 420 | P79: DIRECCION ADMINISTRACION Y FINANZAS | Q79: 4220 | R79: DIRECCION DE ADMINISTRACION | S79: 42230 | T79: GERENCIA DE CONTROL ADMINISTRATIVO | U79: 422303 | V79: SUBDIRECCION DE CONTROL ADMINISTRATIVO | W79: 134111 | X79: LOMAS | Y79: 4 | Z79: CORPORATIVO | AA79: 1 | AB79: NEGOCIO EN MARCHA | AC79: 1 | AD79: BANCO | AE79: 1 | AF79: BACK | AG79: 134111 | AH79: LOMAS | AI79: MPEREZR@BANCOBASE.COM | AJ79: 40603
A80: CLARAG | B80: 2283 | C80: CESAR AUGUSTO LARA GAMIZ | D80: 10025 | E80: COORDINADOR ADMINISTRATIVO REGIONAL MONTERREY Y FORANEAS | F80: MONTERREY | G80: 713 | H80: MONICA GABRIELA PEREZ RAMIREZ | I80: 10026 | J80: GERENTE ADMINISTRATIVO | K80: 1 | L80: PRESIDENCIA EJECUTIVA DEL CONSEJO | M80: 40 | N80: DIRECCION GENERAL BANCO BASE | O80: 420 | P80: DIRECCION ADMINISTRACION Y FINANZAS | Q80: 4220 | R80: DIRECCION DE ADMINISTRACION | S80: 42230 | T80: GERENCIA DE CONTROL ADMINISTRATIVO | U80: 422303 | V80: SUBDIRECCION DE CONTROL ADMINISTRATIVO | W80: 100101 | X80: CORPORATIVO | Y80: 4 | Z80: CORPORATIVO | AA80: 1 | AB80: NEGOCIO EN MARCHA | AC80: 1 | AD80: BANCO | AE80: 1 | AF80: BACK | AG80: 100101 | AH80: CORPORATIVO | AI80: CLARAG@BANCOBASE.COM | AJ80: 43661
A81: FOROZCO | B81: 2976 | C81: FERNANDA SAHIDALY OROZCO VAZQUEZ | D81: 10343 | E81: RESPONSABLE ADMINISTRATIVO CHIHUAHUA | F81: CHIHUAHUA | G81: 2283 | H81: CESAR AUGUSTO LARA GAMIZ | I81: 10025 | J81: COORDINADOR ADMINISTRATIVO REGIONAL MONTERREY Y FORANEAS | K81: 1 | L81: PRESIDENCIA EJECUTIVA DEL CONSEJO | M81: 40 | N81: DIRECCION GENERAL BANCO BASE | O81: 420 | P81: DIRECCION ADMINISTRACION Y FINANZAS | Q81: 4220 | R81: DIRECCION DE ADMINISTRACION | S81: 42230 | T81: GERENCIA DE CONTROL ADMINISTRATIVO | U81: 422317 | V81: ADMINISTRACION CHIHUAHUA | W81: 126131 | X81: CHIHUAHUA | Y81: 4 | Z81: CORPORATIVO | AA81: 1 | AB81: NEGOCIO EN MARCHA | AC81: 1 | AD81: BANCO | AE81: 1 | AF81: BACK | AG81: 126131 | AH81: CHIHUAHUA | AI81: FOROZCO@BANCOBASE.COM | AJ81: 45231
... A138: MPEREZMU | B138: 2682 | C138: MELINA PEREZ MUÑOZ | D138: 8999 | E138: ESPECIALISTA DE ESTRATEGIA TESORERIA | F138: MONTERREY | G138: 3342 | H138: MIGUEL EDUARDO CHAPUS FONSECA | I138: 8451 | J138: OPERADOR DE TESORERIA | K138: 1 | L138: PRESIDENCIA EJECUTIVA DEL CONSEJO | M138: 40 | N138: DIRECCION GENERAL BANCO BASE | O138: 420 | P138: DIRECCION ADMINISTRACION Y FINANZAS | Q138: 4270 | R138: DIRECCION DE TESORERIA | S138: 42700 | T138: DIRECCION DE TESORERIA | U138: 427000 | V138: DIRECCION DE TESORERIA | W138: 100101 | X138: CORPORATIVO | Y138: 4 | Z138: CORPORATIVO | AA138: 1 | AB138: NEGOCIO EN MARCHA | AC138: 1 | AD138: BANCO | AE138: 1 | AF138: BACK | AG138: 100101 | AH138: CORPORATIVO | AI138: MPEREZMU@BANCOBASE.COM | AJ138: 44743
A139: JGARZAL | B139: 878 | C139: JAVIER ALEJANDRO GARZA LEAL | D139: 9948 | E139: DIRECTOR JURIDICO CONTENCIOSO | F139: MONTERREY | I139: 177 | J139: DIRECTOR JURIDICO Y CUMPLIMIENTO | K139: 1 | L139: PRESIDENCIA EJECUTIVA DEL CONSEJO | M139: 40 | N139: DIRECCION GENERAL BANCO BASE | O139: 420 | P139: DIRECCION ADMINISTRACION Y FINANZAS | Q139: 4930 | R139: DIRECCION DE JURIDICO | S139: 49360 | T139: DIRECCION JURIDICO CONTENCIOSO | U139: 493600 | V139: DIRECCION JURIDICO CONTENCIOSO | W139: 100101 | X139: CORPORATIVO | Y139: 4 | Z139: CORPORATIVO | AA139: 1 | AB139: NEGOCIO EN MARCHA | AC139: 1 | AD139: BANCO | AE139: 1 | AF139: BACK | AG139: 100101 | AH139: CORPORATIVO | AI139: JGARZAL@BANCOBASE.COM | AJ139: 41030
A140: NFERNANDEZ | B140: 1755 | C140: NORMA ALICIA FERNANDEZ SALDAÑA | D140: 8359 | E140: GERENTE JURIDICO DE RECUPERACION | F140: MONTERREY | G140: 878 | H140: JAVIER ALEJANDRO GARZA LEAL | I140: 9948 | J140: DIRECTOR JURIDICO CONTENCIOSO | K140: 1 | L140: PRESIDENCIA EJECUTIVA DEL CONSEJO | M140: 40 | N140: DIRECCION GENERAL BANCO BASE | O140: 420 | P140: DIRECCION ADMINISTRACION Y FINANZAS | Q140: 4930 | R140: DIRECCION DE JURIDICO | S140: 49360 | T140: DIRECCION JURIDICO CONTENCIOSO | U140: 493600 | V140: DIRECCION JURIDICO CONTENCIOSO | W140: 100101 | X140: CORPORATIVO | Y140: 4 | Z140: CORPORATIVO | AA140: 1 | AB140: NEGOCIO EN MARCHA | AC140: 1 | AD140: BANCO | AE140: 1 | AF140: BACK | AG140: 100101 | AH140: CORPORATIVO | AI140: NFERNANDEZ@BANCOBASE.COM | AJ140: 42857
A141: MRIOSJ | B141: 3113 | C141: MINERVA DANIELLA RIOS JARQUIN | D141: 8348 | E141: ESPECIALISTA JURIDICO DE RECUPERACION | F141: MONTERREY | G141: 1755 | H141: NORMA ALICIA FERNANDEZ SALDAÑA | I141: 8359 | J141: GERENTE JURIDICO DE RECUPERACION | K141: 1 | L141: PRESIDENCIA EJECUTIVA DEL CONSEJO | M141: 40 | N141: DIRECCION GENERAL BANCO BASE | O141: 420 | P141: DIRECCION ADMINISTRACION Y FINANZAS | Q141: 4930 | R141: DIRECCION DE JURIDICO | S141: 49360 | T141: DIRECCION JURIDICO CONTENCIOSO | U141: 493600 | V141: DIRECCION JURIDICO CONTENCIOSO | W141: 100101 | X141: CORPORATIVO | Y141: 4 | Z141: CORPORATIVO | AA141: 1 | AB141: NEGOCIO EN MARCHA | AC141: 1 | AD141: BANCO | AE141: 1 | AF141: BACK | AG141: 100101 | AH141: CORPORATIVO | AI141: MRIOSJ@BANCOBASE.COM | AJ141: 45428
A142: JGALAVIZ | B142: 3440 | C142: JAIME GALAVIZ CUEVAS | D142: 8559 | E142: ANALISTA JURIDICO DE RECUPERACION | F142: GUADALAJARA | G142: 1755 | H142: NORMA ALICIA FERNANDEZ SALDAÑA | I142: 8359 | J142: GERENTE JURIDICO DE RECUPERACION | K142: 1 | L142: PRESIDENCIA EJECUTIVA DEL CONSEJO | M142: 40 | N142: DIRECCION GENERAL BANCO BASE | O142: 420 | P142: DIRECCION ADMINISTRACION Y FINANZAS | Q142: 4930 | R142: DIRECCION DE JURIDICO | S142: 49360 | T142: DIRECCION JURIDICO CONTENCIOSO | U142: 493600 | V142: DIRECCION JURIDICO CONTENCIOSO | W142: 100101 | X142: CORPORATIVO | Y142: 4 | Z142: CORPORATIVO | AA142: 1 | AB142: NEGOCIO EN MARCHA | AC142: 1 | AD142: BANCO | AE142: 1 | AF142: BACK | AG142: 100101 | AH142: CORPORATIVO | AI142: JGALAVIZ@BANCOBASE.COM | AJ142: 45810
A143: FLEAL | B143: 2756 | C143: FATIMA KARINA LEAL HUERTA | D143: 8012 | E143: ESPECIALISTA JURIDICO DE RECUPERACION | F143: MONTERREY | G143: 1755 | H143: NORMA ALICIA FERNANDEZ SALDAÑA | I143: 8359 | J143: GERENTE JURIDICO DE RECUPERACION | K143: 1 | L143: PRESIDENCIA EJECUTIVA DEL CONSEJO | M143: 40 | N143: DIRECCION GENERAL BANCO BASE | O143: 420 | P143: DIRECCION ADMINISTRACION Y FINANZAS | Q143: 4930 | R143: DIRECCION DE JURIDICO | S143: 49360 | T143: DIRECCION JURIDICO CONTENCIOSO | U143: 493600 | V143: DIRECCION JURIDICO CONTENCIOSO | W143: 100101 | X143: CORPORATIVO | Y143: 4 | Z143: CORPORATIVO | AA143: 1 | AB143: NEGOCIO EN MARCHA | AC143: 1 | AD143: BANCO | AE143: 1 | AF143: BACK | AG143: 100101 | AH143: CORPORATIVO | AI143: FLEAL@BANCOBASE.COM | AJ143: 44851
A144: RMARTINERO | B144: 2203 | C144: ROCIO ARACELY MARTINEZ RODRIGUEZ | D144: 8360 | E144: GERENTE JURIDICO DE RESPUESTA A AUTORIDADES | F144: MONTERREY | G144: 878 | H144: JAVIER ALEJANDRO GARZA LEAL | I144: 9948 | J144: DIRECTOR JURIDICO CONTENCIOSO | K144: 1 | L144: PRESIDENCIA EJECUTIVA DEL CONSEJO | M144: 40 | N144: DIRECCION GENERAL BANCO BASE | O144: 420 | P144: DIRECCION ADMINISTRACION Y FINANZAS | Q144: 4930 | R144: DIRECCION DE JURIDICO | S144: 49360 | T144: DIRECCION JURIDICO CONTENCIOSO | U144: 493600 | V144: DIRECCION JURIDICO CONTENCIOSO | W144: 100101 | X144: CORPORATIVO | Y144: 4 | Z144: CORPORATIVO | AA144: 1 | AB144: NEGOCIO EN MARCHA | AC144: 1 | AD144: BANCO | AE144: 1 | AF144: BACK | AG144: 100101 | AH144: CORPORATIVO | AI144: RMARTINERO@BANCOBASE.COM | AJ144: 43545
A145: EBUENO | B145: 2098 | C145: SANDRA ESMERALDA BUENO PEÑA | D145: 8022 | E145: ANALISTA JURIDICO DE RESPUESTA A AUTORIDADES | F145: MONTERREY | G145: 2203 | H145: ROCIO ARACELY MARTINEZ RODRIGUEZ | I145: 8360 | J145: GERENTE JURIDICO DE RESPUESTA A AUTORIDADES | K145: 1 | L145: PRESIDENCIA EJECUTIVA DEL CONSEJO | M145: 40 | N145: DIRECCION GENERAL BANCO BASE | O145: 420 | P145: DIRECCION ADMINISTRACION Y FINANZAS | Q145: 4930 | R145: DIRECCION DE JURIDICO | S145: 49360 | T145: DIRECCION JURIDICO CONTENCIOSO | U145: 493600 | V145: DIRECCION JURIDICO CONTENCIOSO | W145: 100101 | X145: CORPORATIVO | Y145: 4 | Z145: CORPORATIVO | AA145: 6 | AB145: PROYECTO REGULATORIOS | AC145: 1 | AD145: BANCO | AE145: 1 | AF145: BACK | AG145: 100101 | AH145: CORPORATIVO | AI145: EBUENO@BANCOBASE.COM | AJ145: 43359
A146: GSANTIAGO | B146: 99536 | C146: GABRIELA TONANTZIN SANTIAGO OLMOS | D146: 7013 | E146: PRACTICANTE | F146: MONTERREY | G146: 2203 | H146: ROCIO ARACELY MARTINEZ RODRIGUEZ | I146: 8360 | J146: GERENTE JURIDICO DE RESPUESTA A AUTORIDADES | K146: 1 | L146: PRESIDENCIA EJECUTIVA DEL CONSEJO | M146: 40 | N146: DIRECCION GENERAL BANCO BASE | O146: 420 | P146: DIRECCION ADMINISTRACION Y FINANZAS | Q146: 4930 | R146: DIRECCION DE JURIDICO | S146: 49360 | T146: DIRECCION JURIDICO CONTENCIOSO | U146: 493600 | V146: DIRECCION JURIDICO CONTENCIOSO | W146: 100101 | X146: CORPORATIVO | Y146: 4 | Z146: CORPORATIVO | AA146: 1 | AB146: NEGOCIO EN MARCHA | AC146: 1 | AD146: BANCO | AE146: 1 | AF146: BACK | AG146: 100101 | AH146: CORPORATIVO | AI146: GSANTIAGO@BANCOBASE.COM | AJ146: 46128
A147: JAGUILARGA | B147: 3938 | C147: JORDI AGUILAR GARCIA | D147: 8224 | E147: ANALISTA JURIDICO DE RESPUESTA A AUTORIDADES | F147: MONTERREY | G147: 2203 | H147: ROCIO ARACELY MARTINEZ RODRIGUEZ | I147: 8360 | J147: GERENTE JURIDICO DE RESPUESTA A AUTORIDADES | K147: 1 | L147: PRESIDENCIA EJECUTIVA DEL CONSEJO | M147: 40 | N147: DIRECCION GENERAL BANCO BASE | O147: 420 | P147: DIRECCION ADMINISTRACION Y FINANZAS | Q147: 4930 | R147: DIRECCION DE JURIDICO | S147: 49360 | T147: DIRECCION JURIDICO CONTENCIOSO | U147: 493600 | V147: DIRECCION JURIDICO CONTENCIOSO | W147: 100101 | X147: CORPORATIVO | Y147: 4 | Z147: CORPORATIVO | AA147: 6 | AB147: PROYECTO REGULATORIOS | AC147: 1 | AD147: BANCO | AE147: 1 | AF147: BACK | AG147: 100101 | AH147: CORPORATIVO | AI147: JAGUILARGA@BANCOBASE.COM | AJ147: 46219
A148: GVEGA | B148: 3020 | C148: GERARDO ROGELIO VEGA VERDUGO | D148: 425 | E148: RESPONSABLE JURIDICO CONTENCIOSO | F148: MONTERREY | G148: 878 | H148: JAVIER ALEJANDRO GARZA LEAL | I148: 9948 | J148: DIRECTOR JURIDICO CONTENCIOSO | K148: 1 | L148: PRESIDENCIA EJECUTIVA DEL CONSEJO | M148: 40 | N148: DIRECCION GENERAL BANCO BASE | O148: 420 | P148: DIRECCION ADMINISTRACION Y FINANZAS | Q148: 4930 | R148: DIRECCION DE JURIDICO | S148: 49360 | T148: DIRECCION JURIDICO CONTENCIOSO | U148: 493600 | V148: DIRECCION JURIDICO CONTENCIOSO | W148: 100101 | X148: CORPORATIVO | Y148: 4 | Z148: CORPORATIVO | AA148: 1 | AB148: NEGOCIO EN MARCHA | AC148: 1 | AD148: BANCO | AE148: 1 | AF148: BACK | AG148: 100101 | AH148: CORPORATIVO | AI148: GVEGA@BANCOBASE.COM | AJ148: 45323
A149: MMEDINA | B149: 99533 | C149: MARIANA SOPHIA MEDINA LEAL | D149: 10144 | E149: PRACTICANTE | F149: MONTERREY | G149: 3020 | H149: GERARDO ROGELIO VEGA VERDUGO | I149: 425 | J149: RESPONSABLE JURIDICO CONTENCIOSO | K149: 1 | L149: PRESIDENCIA EJECUTIVA DEL CONSEJO | M149: 40 | N149: DIRECCION GENERAL BANCO BASE | O149: 420 | P149: DIRECCION ADMINISTRACION Y FINANZAS | Q149: 4930 | R149: DIRECCION DE JURIDICO | S149: 49360 | T149: DIRECCION JURIDICO CONTENCIOSO | U149: 493600 | V149: DIRECCION JURIDICO CONTENCIOSO | W149: 100101 | X149: CORPORATIVO | Y149: 4 | Z149: CORPORATIVO | AA149: 1 | AB149: NEGOCIO EN MARCHA | AC149: 1 | AD149: BANCO | AE149: 1 | AF149: BACK | AG149: 100101 | AH149: CORPORATIVO | AI149: MMEDINA@BANCOBASE.COM | AJ149: 46098
A150: CGONZALEZN | B150: 3135 | C150: CAROLINA FRANCHESKA GONZALEZ NAVARRO | D150: 8732 | E150: ESPECIALISTA JURIDICO CONTENCIOSO | F150: MONTERREY | G150: 878 | H150: JAVIER ALEJANDRO GARZA LEAL | I150: 9948 | J150: DIRECTOR JURIDICO CONTENCIOSO | K150: 1 | L150: PRESIDENCIA EJECUTIVA DEL CONSEJO | M150: 40 | N150: DIRECCION GENERAL BANCO BASE | O150: 420 | P150: DIRECCION ADMINISTRACION Y FINANZAS | Q150: 4930 | R150: DIRECCION DE JURIDICO | S150: 49360 | T150: DIRECCION JURIDICO CONTENCIOSO | U150: 493600 | V150: DIRECCION JURIDICO CONTENCIOSO | W150: 100101 | X150: CORPORATIVO | Y150: 4 | Z150: CORPORATIVO | AA150: 1 | AB150: NEGOCIO EN MARCHA | AC150: 1 | AD150: BANCO | AE150: 1 | AF150: BACK | AG150: 100101 | AH150: CORPORATIVO | AI150: CGONZALEZN@BANCOBASE.COM | AJ150: 45460
A151: IGARCIA | B151: 923 | C151: IVETTE GUADALUPE GARCIA ALVAREZ | D151: 9341 | E151: SUBDIRECTOR JURIDICO TRANSACCIONAL | F151: MONTERREY | I151: 177 | J151: DIRECTOR JURIDICO Y CUMPLIMIENTO | K151: 1 | L151: PRESIDENCIA EJECUTIVA DEL CONSEJO | M151: 40 | N151: DIRECCION GENERAL BANCO BASE | O151: 420 | P151: DIRECCION ADMINISTRACION Y FINANZAS | Q151: 4930 | R151: DIRECCION DE JURIDICO | S151: 49330 | T151: SUBDIRECCION JURIDICO TRANSACCIONAL | U151: 493300 | V151: SUBDIRECCION JURIDICO TRANSACCIONAL | W151: 100101 | X151: CORPORATIVO | Y151: 9 | Z151: BANCARIO | AA151: 1 | AB151: NEGOCIO EN MARCHA | AC151: 1 | AD151: BANCO | AE151: 1 | AF151: BACK | AG151: 100101 | AH151: CORPORATIVO | AI151: IGARCIA@BANCOBASE.COM | AJ151: 41122
A152: EESQUEDA | B152: 1837 | C152: ERICK EDUARDO ESQUEDA LOYA | D152: 10295 | E152: GERENTE JURIDICO DE CONTRATACION | F152: MONTERREY | G152: 923 | H152: IVETTE GUADALUPE GARCIA ALVAREZ | I152: 9341 | J152: SUBDIRECTOR JURIDICO TRANSACCIONAL | K152: 1 | L152: PRESIDENCIA EJECUTIVA DEL CONSEJO | M152: 40 | N152: DIRECCION GENERAL BANCO BASE | O152: 420 | P152: DIRECCION ADMINISTRACION Y FINANZAS | Q152: 4930 | R152: DIRECCION DE JURIDICO | S152: 49330 | T152: SUBDIRECCION JURIDICO TRANSACCIONAL | U152: 493300 | V152: SUBDIRECCION JURIDICO TRANSACCIONAL | W152: 100101 | X152: CORPORATIVO | Y152: 4 | Z152: CORPORATIVO | AA152: 1 | AB152: NEGOCIO EN MARCHA | AC152: 1 | AD152: BANCO | AE152: 1 | AF152: BACK | AG152: 100101 | AH152: CORPORATIVO | AI152: EESQUEDA@BANCOBASE.COM | AJ152: 42982
A153: FHERNANDEG | B153: 2654 | C153: MARIA FERNANDA HERNANDEZ GAYTAN | D153: 9530 | E153: ANALISTA JURIDICO DE CONTRATACION | F153: MONTERREY | G153: 1837 | H153: ERICK EDUARDO ESQUEDA LOYA | I153: 10295 | J153: GERENTE JURIDICO DE CONTRATACION | K153: 1 | L153: PRESIDENCIA EJECUTIVA DEL CONSEJO | M153: 40 | N153: DIRECCION GENERAL BANCO BASE | O153: 420 | P153: DIRECCION ADMINISTRACION Y FINANZAS | Q153: 4930 | R153: DIRECCION DE JURIDICO | S153: 49330 | T153: SUBDIRECCION JURIDICO TRANSACCIONAL | U153: 493300 | V153: SUBDIRECCION JURIDICO TRANSACCIONAL | W153: 100101 | X153: CORPORATIVO | Y153: 9 | Z153: BANCARIO | AA153: 1 | AB153: NEGOCIO EN MARCHA | AC153: 1 | AD153: BANCO | AE153: 1 | AF153: BACK | AG153: 100101 | AH153: CORPORATIVO | AI153: FHERNANDEG@BANCOBASE.COM | AJ153: 44697
A154: LGARCIAGO | B154: 2653 | C154: LUISANA SOFIA GARCIA GONZALEZ | D154: 9180 | E154: ANALISTA JURIDICO DE CONTRATACION | F154: MONTERREY | G154: 1837 | H154: ERICK EDUARDO ESQUEDA LOYA | I154: 10295 | J154: GERENTE JURIDICO DE CONTRATACION | K154: 1 | L154: PRESIDENCIA EJECUTIVA DEL CONSEJO | M154: 40 | N154: DIRECCION GENERAL BANCO BASE | O154: 420 | P154: DIRECCION ADMINISTRACION Y FINANZAS | Q154: 4930 | R154: DIRECCION DE JURIDICO | S154: 49330 | T154: SUBDIRECCION JURIDICO TRANSACCIONAL | U154: 493300 | V154: SUBDIRECCION JURIDICO TRANSACCIONAL | W154: 100101 | X154: CORPORATIVO | Y154: 9 | Z154: BANCARIO | AA154: 1 | AB154: NEGOCIO EN MARCHA | AC154: 1 | AD154: BANCO | AE154: 1 | AF154: BACK | AG154: 100101 | AH154: CORPORATIVO | AI154: LGARCIAGO@BANCOBASE.COM | AJ154: 44697
A155: ASGONZALEZ | B155: 1896 | C155: ARTURO SANTIAGO GONZALEZ CARRILLO | D155: 8124 | E155: GERENTE JURIDICO DE DICTAMINACION | F155: MONTERREY | G155: 923 | H155: IVETTE GUADALUPE GARCIA ALVAREZ | I155: 9341 | J155: SUBDIRECTOR JURIDICO TRANSACCIONAL | K155: 1 | L155: PRESIDENCIA EJECUTIVA DEL CONSEJO | M155: 40 | N155: DIRECCION GENERAL BANCO BASE | O155: 420 | P155: DIRECCION ADMINISTRACION Y FINANZAS | Q155: 4930 | R155: DIRECCION DE JURIDICO | S155: 49330 | T155: SUBDIRECCION JURIDICO TRANSACCIONAL | U155: 493300 | V155: SUBDIRECCION JURIDICO TRANSACCIONAL | W155: 100101 | X155: CORPORATIVO | Y155: 9 | Z155: BANCARIO | AA155: 1 | AB155: NEGOCIO EN MARCHA | AC155: 1 | AD155: BANCO | AE155: 1 | AF155: BACK | AG155: 100101 | AH155: CORPORATIVO | AI155: ASGONZALEZ@BANCOBASE.COM | AJ155: 43070
A156: JVALENZUEV | B156: 2487 | C156: JESUS EMILIANO VALENZUELA VALLEJO | D156: 8126 | E156: ESPECIALISTA JURIDICO DE DICTAMINACION | F156: MONTERREY | G156: 1896 | H156: ARTURO SANTIAGO GONZALEZ CARRILLO | I156: 8124 | J156: GERENTE JURIDICO DE DICTAMINACION | K156: 1 | L156: PRESIDENCIA EJECUTIVA DEL CONSEJO | M156: 40 | N156: DIRECCION GENERAL BANCO BASE | O156: 420 | P156: DIRECCION ADMINISTRACION Y FINANZAS | Q156: 4930 | R156: DIRECCION DE JURIDICO | S156: 49330 | T156: SUBDIRECCION JURIDICO TRANSACCIONAL | U156: 493300 | V156: SUBDIRECCION JURIDICO TRANSACCIONAL | W156: 100101 | X156: CORPORATIVO | Y156: 4 | Z156: CORPORATIVO | AA156: 1 | AB156: NEGOCIO EN MARCHA | AC156: 1 | AD156: BANCO | AE156: 1 | AF156: BACK | AG156: 100101 | AH156: CORPORATIVO | AI156: JVALENZUEV@BANCOBASE.COM | AJ156: 44271
A157: EGALLEGOS | B157: 2871 | C157: ELIZABETH GALLEGOS BARAJAS | D157: 10126 | E157: ANALISTA JURIDICO DE DICTAMINACION SR | F157: MONTERREY | G157: 1896 | H157: ARTURO SANTIAGO GONZALEZ CARRILLO | I157: 8124 | J157: GERENTE JURIDICO DE DICTAMINACION | K157: 1 | L157: PRESIDENCIA EJECUTIVA DEL CONSEJO | M157: 40 | N157: DIRECCION GENERAL BANCO BASE | O157: 420 | P157: DIRECCION ADMINISTRACION Y FINANZAS | Q157: 4930 | R157: DIRECCION DE JURIDICO | S157: 49330 | T157: SUBDIRECCION JURIDICO TRANSACCIONAL | U157: 493300 | V157: SUBDIRECCION JURIDICO TRANSACCIONAL | W157: 100101 | X157: CORPORATIVO | Y157: 4 | Z157: CORPORATIVO | AA157: 1 | AB157: NEGOCIO EN MARCHA | AC157: 1 | AD157: BANCO | AE157: 1 | AF157: BACK | AG157: 100101 | AH157: CORPORATIVO | AI157: EGALLEGOS@BANCOBASE.COM | AJ157: 45019
A158: AALVAREZS | B158: 3049 | C158: ANDREA MICHELLE ALVAREZ SILVA | D158: 9022 | E158: ANALISTA JURIDICO DE DICTAMINACION JR | F158: MONTERREY | G158: 1896 | H158: ARTURO SANTIAGO GONZALEZ CARRILLO | I158: 8124 | J158: GERENTE JURIDICO DE DICTAMINACION | K158: 1 | L158: PRESIDENCIA EJECUTIVA DEL CONSEJO | M158: 40 | N158: DIRECCION GENERAL BANCO BASE | O158: 420 | P158: DIRECCION ADMINISTRACION Y FINANZAS | Q158: 4930 | R158: DIRECCION DE JURIDICO | S158: 49330 | T158: SUBDIRECCION JURIDICO TRANSACCIONAL | U158: 493300 | V158: SUBDIRECCION JURIDICO TRANSACCIONAL | W158: 100101 | X158: CORPORATIVO | Y158: 4 | Z158: CORPORATIVO | AA158: 1 | AB158: NEGOCIO EN MARCHA | AC158: 1 | AD158: BANCO | AE158: 1 | AF158: BACK | AG158: 100101 | AH158: CORPORATIVO | AI158: AALVAREZS@BANCOBASE.COM | AJ158: 45357
A159: CCASTILLOL | B159: 3481 | C159: CAROLINA CASTILLO LIMON | D159: 9721 | E159: ANALISTA JURIDICO DE DICTAMINACION JR | F159: MONTERREY | G159: 1896 | H159: ARTURO SANTIAGO GONZALEZ CARRILLO | I159: 8124 | J159: GERENTE JURIDICO DE DICTAMINACION | K159: 1 | L159: PRESIDENCIA EJECUTIVA DEL CONSEJO | M159: 40 | N159: DIRECCION GENERAL BANCO BASE | O159: 420 | P159: DIRECCION ADMINISTRACION Y FINANZAS | Q159: 4930 | R159: DIRECCION DE JURIDICO | S159: 49330 | T159: SUBDIRECCION JURIDICO TRANSACCIONAL | U159: 493300 | V159: SUBDIRECCION JURIDICO TRANSACCIONAL | W159: 100101 | X159: CORPORATIVO | Y159: 4 | Z159: CORPORATIVO | AA159: 1 | AB159: NEGOCIO EN MARCHA | AC159: 1 | AD159: BANCO | AE159: 1 | AF159: BACK | AG159: 100101 | AH159: CORPORATIVO | AI159: CCASTILLOL@BANCOBASE.COM | AJ159: 45854
A160: CMARTINEV | B160: 2967 | C160: CESAR ALAN MARTINEZ VILLARREAL | D160: 10415 | E160: ANALISTA JURIDICO DE DICTAMINACION SR | F160: MONTERREY | G160: 1896 | H160: ARTURO SANTIAGO GONZALEZ CARRILLO | I160: 8124 | J160: GERENTE JURIDICO DE DICTAMINACION | K160: 1 | L160: PRESIDENCIA EJECUTIVA DEL CONSEJO | M160: 40 | N160: DIRECCION GENERAL BANCO BASE | O160: 420 | P160: DIRECCION ADMINISTRACION Y FINANZAS | Q160: 4930 | R160: DIRECCION DE JURIDICO | S160: 49330 | T160: SUBDIRECCION JURIDICO TRANSACCIONAL | U160: 493300 | V160: SUBDIRECCION JURIDICO TRANSACCIONAL | W160: 100101 | X160: CORPORATIVO | Y160: 4 | Z160: CORPORATIVO | AA160: 1 | AB160: NEGOCIO EN MARCHA | AC160: 1 | AD160: BANCO | AE160: 1 | AF160: BACK | AG160: 100101 | AH160: CORPORATIVO | AI160: CMARTINEV@BANCOBASE.COM | AJ160: 45201
A161: MBAZALDUA | B161: 3739 | C161: MIGUEL ALAN BAZALDUA BERNAL | D161: 8770 | E161: ANALISTA JURIDICO DE DICTAMINACION JR | F161: MONTERREY | G161: 1896 | H161: ARTURO SANTIAGO GONZALEZ CARRILLO | I161: 8124 | J161: GERENTE JURIDICO DE DICTAMINACION | K161: 1 | L161: PRESIDENCIA EJECUTIVA DEL CONSEJO | M161: 40 | N161: DIRECCION GENERAL BANCO BASE | O161: 420 | P161: DIRECCION ADMINISTRACION Y FINANZAS | Q161: 4930 | R161: DIRECCION DE JURIDICO | S161: 49330 | T161: SUBDIRECCION JURIDICO TRANSACCIONAL | U161: 493300 | V161: SUBDIRECCION JURIDICO TRANSACCIONAL | W161: 100101 | X161: CORPORATIVO | Y161: 9 | Z161: BANCARIO | AA161: 1 | AB161: NEGOCIO EN MARCHA | AC161: 1 | AD161: BANCO | AE161: 1 | AF161: BACK | AG161: 100101 | AH161: CORPORATIVO | AI161: MBAZALDUA@BANCOBASE.COM | AJ161: 46041
A162: SIBARRA | B162: 3770 | C162: SILOE EMMANUEL IBARRA FLORES | D162: 8151 | E162: ANALISTA JURIDICO DE DICTAMINACION JR | F162: MONTERREY | G162: 1896 | H162: ARTURO SANTIAGO GONZALEZ CARRILLO | I162: 8124 | J162: GERENTE JURIDICO DE DICTAMINACION | K162: 1 | L162: PRESIDENCIA EJECUTIVA DEL CONSEJO | M162: 40 | N162: DIRECCION GENERAL BANCO BASE | O162: 420 | P162: DIRECCION ADMINISTRACION Y FINANZAS | Q162: 4930 | R162: DIRECCION DE JURIDICO | S162: 49330 | T162: SUBDIRECCION JURIDICO TRANSACCIONAL | U162: 493300 | V162: SUBDIRECCION JURIDICO TRANSACCIONAL | W162: 100101 | X162: CORPORATIVO | Y162: 9 | Z162: BANCARIO | AA162: 1 | AB162: NEGOCIO EN MARCHA | AC162: 1 | AD162: BANCO | AE162: 1 | AF162: BACK | AG162: 100101 | AH162: CORPORATIVO | AI162: SIBARRA@BANCOBASE.COM | AJ162: 46082
A163: RAGUILARB | B163: 99534 | C163: REBECA AGUILAR BRICEÑO | D163: 7008 | E163: PRACTICANTE | F163: MONTERREY | G163: 1896 | H163: ARTURO SANTIAGO GONZALEZ CARRILLO | I163: 8124 | J163: GERENTE JURIDICO DE DICTAMINACION | K163: 1 | L163: PRESIDENCIA EJECUTIVA DEL CONSEJO | M163: 40 | N163: DIRECCION GENERAL BANCO BASE | O163: 420 | P163: DIRECCION ADMINISTRACION Y FINANZAS | Q163: 4930 | R163: DIRECCION DE JURIDICO | S163: 49330 | T163: SUBDIRECCION JURIDICO TRANSACCIONAL | U163: 493300 | V163: SUBDIRECCION JURIDICO TRANSACCIONAL | W163: 100101 | X163: CORPORATIVO | Y163: 4 | Z163: CORPORATIVO | AA163: 1 | AB163: NEGOCIO EN MARCHA | AC163: 1 | AD163: BANCO | AE163: 1 | AF163: BACK | AG163: 100101 | AH163: CORPORATIVO | AI163: RAGUILARB@BANCOBASE.COM | AJ163: 46118
... A176: ABOSQUE | B176: 2740 | C176: ANTONIO DEL BOSQUE FANTI | D176: 9720 | E176: ANALISTA JURIDICO SR NUEVOS NEGOCIOS | F176: MONTERREY | G176: 2986 | H176: JOSUE YOZAFAT LUNA PEREZ | I176: 517731 | J176: GERENTE JURIDICO DE NUEVOS PRODUCTOS Y NEGOCIOS | K176: 1 | L176: PRESIDENCIA EJECUTIVA DEL CONSEJO | M176: 40 | N176: DIRECCION GENERAL BANCO BASE | O176: 420 | P176: DIRECCION ADMINISTRACION Y FINANZAS | Q176: 4930 | R176: DIRECCION DE JURIDICO | S176: 49350 | T176: JURIDICO DE NUEVOS PRODUCTOS Y MERCADOS FINANCIERO | U176: 493500 | V176: JURIDICO DE NUEVOS PRODUCTOS Y MERCADOS FINANCIERO | W176: 100101 | X176: CORPORATIVO | Y176: 9 | Z176: BANCARIO | AA176: 1 | AB176: NEGOCIO EN MARCHA | AC176: 1 | AD176: BANCO | AE176: 1 | AF176: BACK | AG176: 100101 | AH176: CORPORATIVO | AI176: ABOSQUE@BANCOBASE.COM | AJ176: 44837
A177: LHERNANDEP | B177: 2120 | C177: ANA LUCIA HERNANDEZ PINEDA | D177: 8256 | E177: SUBDIRECTOR JURIDICO CORPORATIVO | F177: MONTERREY | I177: 177 | J177: DIRECTOR JURIDICO Y CUMPLIMIENTO | K177: 1 | L177: PRESIDENCIA EJECUTIVA DEL CONSEJO | M177: 40 | N177: DIRECCION GENERAL BANCO BASE | O177: 420 | P177: DIRECCION ADMINISTRACION Y FINANZAS | Q177: 4930 | R177: DIRECCION DE JURIDICO | S177: 49320 | T177: GOBIERNO CORPORATIVO | U177: 493200 | V177: GOBIERNO CORPORATIVO | W177: 100101 | X177: CORPORATIVO | Y177: 4 | Z177: CORPORATIVO | AA177: 1 | AB177: NEGOCIO EN MARCHA | AC177: 1 | AD177: BANCO | AE177: 1 | AF177: BACK | AG177: 100101 | AH177: CORPORATIVO | AI177: LHERNANDEP@BANCOBASE.COM | AJ177: 43389
A178: DVAZQUEZI | B178: 2333 | C178: DIANA CAROLINA VAZQUEZ IRIGOYEN | D178: 9531 | E178: COORDINADOR JURIDICO CORPORATIVO | F178: MONTERREY | G178: 2120 | H178: ANA LUCIA HERNANDEZ PINEDA | I178: 8256 | J178: SUBDIRECTOR JURIDICO CORPORATIVO | K178: 1 | L178: PRESIDENCIA EJECUTIVA DEL CONSEJO | M178: 40 | N178: DIRECCION GENERAL BANCO BASE | O178: 420 | P178: DIRECCION ADMINISTRACION Y FINANZAS | Q178: 4930 | R178: DIRECCION DE JURIDICO | S178: 49320 | T178: GOBIERNO CORPORATIVO | U178: 493200 | V178: GOBIERNO CORPORATIVO | W178: 100101 | X178: CORPORATIVO | Y178: 4 | Z178: CORPORATIVO | AA178: 1 | AB178: NEGOCIO EN MARCHA | AC178: 1 | AD178: BANCO | AE178: 1 | AF178: BACK | AG178: 100101 | AH178: CORPORATIVO | AI178: DVAZQUEZI@BANCOBASE.COM | AJ178: 43739
A179: AGUERREROM | B179: 3855 | C179: ANDREA GUERRERO MORALES | D179: 8300 | E179: ANALISTA JURIDICO CORPORATIVO | F179: MONTERREY | G179: 2333 | H179: DIANA CAROLINA VAZQUEZ IRIGOYEN | I179: 9531 | J179: COORDINADOR JURIDICO CORPORATIVO | K179: 1 | L179: PRESIDENCIA EJECUTIVA DEL CONSEJO | M179: 40 | N179: DIRECCION GENERAL BANCO BASE | O179: 420 | P179: DIRECCION ADMINISTRACION Y FINANZAS | Q179: 4930 | R179: DIRECCION DE JURIDICO | S179: 49320 | T179: GOBIERNO CORPORATIVO | U179: 493200 | V179: GOBIERNO CORPORATIVO | W179: 100101 | X179: CORPORATIVO | Y179: 4 | Z179: CORPORATIVO | AA179: 1 | AB179: NEGOCIO EN MARCHA | AC179: 1 | AD179: BANCO | AE179: 1 | AF179: BACK | AG179: 100101 | AH179: CORPORATIVO | AI179: AGUERREROM@BANCOBASE.COM | AJ179: 46146
A180: HCPENA | B180: 2687 | C180: HILDA YARELY DE LA CERDA PEÑA | D180: 8257 | E180: COORDINADOR DE SERVICIOS JURIDICOS | F180: MONTERREY | G180: 2120 | H180: ANA LUCIA HERNANDEZ PINEDA | I180: 8256 | J180: SUBDIRECTOR JURIDICO CORPORATIVO | K180: 1 | L180: PRESIDENCIA EJECUTIVA DEL CONSEJO | M180: 40 | N180: DIRECCION GENERAL BANCO BASE | O180: 420 | P180: DIRECCION ADMINISTRACION Y FINANZAS | Q180: 4930 | R180: DIRECCION DE JURIDICO | S180: 49320 | T180: GOBIERNO CORPORATIVO | U180: 493200 | V180: GOBIERNO CORPORATIVO | W180: 100101 | X180: CORPORATIVO | Y180: 4 | Z180: CORPORATIVO | AA180: 1 | AB180: NEGOCIO EN MARCHA | AC180: 1 | AD180: BANCO | AE180: 1 | AF180: BACK | AG180: 100101 | AH180: CORPORATIVO | AI180: HCPENA@BANCOBASE.COM | AJ180: 44746
A181: MGARZAFU | B181: 2987 | C181: MICHELLE GARZA FUENTES | D181: 10035 | E181: ANALISTA JURIDICO DE CONTRATACION DE PROVEEDORES | F181: MONTERREY | G181: 2687 | H181: HILDA YARELY DE LA CERDA PEÑA | I181: 8257 | J181: COORDINADOR DE SERVICIOS JURIDICOS | K181: 1 | L181: PRESIDENCIA EJECUTIVA DEL CONSEJO | M181: 40 | N181: DIRECCION GENERAL BANCO BASE | O181: 420 | P181: DIRECCION ADMINISTRACION Y FINANZAS | Q181: 4930 | R181: DIRECCION DE JURIDICO | S181: 49320 | T181: GOBIERNO CORPORATIVO | U181: 493200 | V181: GOBIERNO CORPORATIVO | W181: 100101 | X181: CORPORATIVO | Y181: 4 | Z181: CORPORATIVO | AA181: 1 | AB181: NEGOCIO EN MARCHA | AC181: 1 | AD181: BANCO | AE181: 1 | AF181: BACK | AG181: 100101 | AH181: CORPORATIVO | AI181: MGARZAFU@BANCOBASE.COM | AJ181: 45246
A182: AVERA | B182: 3574 | C182: ANDREA VERA FLORES | D182: 8111 | E182: ANALISTA JURIDICO DE CONTRATACION DE PROVEEDORES | F182: MONTERREY | G182: 2687 | H182: HILDA YARELY DE LA CERDA PEÑA | I182: 8257 | J182: COORDINADOR DE SERVICIOS JURIDICOS | K182: 1 | L182: PRESIDENCIA EJECUTIVA DEL CONSEJO | M182: 40 | N182: DIRECCION GENERAL BANCO BASE | O182: 420 | P182: DIRECCION ADMINISTRACION Y FINANZAS | Q182: 4930 | R182: DIRECCION DE JURIDICO | S182: 49320 | T182: GOBIERNO CORPORATIVO | U182: 493200 | V182: GOBIERNO CORPORATIVO | W182: 100101 | X182: CORPORATIVO | Y182: 4 | Z182: CORPORATIVO | AA182: 1 | AB182: NEGOCIO EN MARCHA | AC182: 1 | AD182: BANCO | AE182: 1 | AF182: BACK | AG182: 100101 | AH182: CORPORATIVO | AI182: AVERA@BANCOBASE.COM | AJ182: 45917
A183: XLOPEZ | B183: 1575 | C183: XOCHITL MAYRA LOPEZ TAPIA | D183: 8213 | E183: LIDER DE MEJORA CONTINUA, TRANSFORMACION Y LEGALTECH | F183: MONTERREY | I183: 177 | J183: DIRECTOR JURIDICO Y CUMPLIMIENTO | K183: 1 | L183: PRESIDENCIA EJECUTIVA DEL CONSEJO | M183: 40 | N183: DIRECCION GENERAL BANCO BASE | O183: 420 | P183: DIRECCION ADMINISTRACION Y FINANZAS | Q183: 4930 | R183: DIRECCION DE JURIDICO | S183: 49300 | T183: DIRECCION DE JURIDICO | U183: 493000 | V183: DIRECCION DE JURIDICO | W183: 100101 | X183: CORPORATIVO | Y183: 9 | Z183: BANCARIO | AA183: 1 | AB183: NEGOCIO EN MARCHA | AC183: 1 | AD183: BANCO | AE183: 1 | AF183: BACK | AG183: 100101 | AH183: CORPORATIVO | AI183: XLOPEZ@BANCOBASE.COM | AJ183: 42522
A184: LRAMOSA | B184: 2909 | C184: LESLY AZENETH RAMOS ALVAREZ | D184: 8968 | E184: BUSINESS PARTNER PROCUREMENT | F184: MONTERREY | G184: 2529 | H184: ENRIQUE EDUARDO GALEANA UGALDE | I184: 7 | J184: DIRECTOR DE ADMINISTRACION Y FINANZAS | K184: 1 | L184: PRESIDENCIA EJECUTIVA DEL CONSEJO | M184: 40 | N184: DIRECCION GENERAL BANCO BASE | O184: 420 | P184: DIRECCION ADMINISTRACION Y FINANZAS | Q184: 4200 | R184: DIRECCION ADMINISTRACION Y FINANZAS | S184: 42000 | T184: DIRECCION ADMINISTRACION Y FINANZAS | U184: 420000 | V184: DIRECCION ADMINISTRACION Y FINANZAS | W184: 100101 | X184: CORPORATIVO | Y184: 4 | Z184: CORPORATIVO | AA184: 1 | AB184: NEGOCIO EN MARCHA | AC184: 1 | AD184: BANCO | AE184: 1 | AF184: BACK | AG184: 100101 | AH184: CORPORATIVO | AI184: LRAMOSA@BANCOBASE.COM | AJ184: 45093
A185: SCORTES | B185: 989 | C185: SERGIO CORTES FERNANDEZ | D185: 1007 | E185: DIRECTOR DE CONTRALORIA Y PREVENCION | F185: MONTERREY | G185: 386 | H185: JULIO RICARDO ESCANDON JIMENEZ | I185: 10324 | J185: DIRECTOR GENERAL | K185: 1 | L185: PRESIDENCIA EJECUTIVA DEL CONSEJO | M185: 40 | N185: DIRECCION GENERAL BANCO BASE | O185: 440 | P185: DIRECCION DE CONTRALORIA Y PREVENCION | Q185: 4400 | R185: DIRECCION DE CONTRALORIA Y PREVENCION | S185: 44000 | T185: DIRECCION DE CONTRALORIA Y PREVENCION | U185: 440000 | V185: DIRECCION DE CONTRALORIA Y PREVENCION | W185: 100101 | X185: CORPORATIVO | Y185: 4 | Z185: CORPORATIVO | AA185: 1 | AB185: NEGOCIO EN MARCHA | AC185: 1 | AD185: BANCO | AE185: 1 | AF185: BACK | AG185: 100101 | AH185: CORPORATIVO | AI185: SCORTES@BANCOBASE.COM | AJ185: 41306
A186: NGALLEGOS | B186: 618 | C186: NANCY GALLEGOS RUIZ | D186: 8387 | E186: DIRECTOR DE OPERACIONES | F186: MONTERREY | G186: 989 | H186: SERGIO CORTES FERNANDEZ | I186: 1007 | J186: DIRECTOR DE CONTRALORIA Y PREVENCION | K186: 1 | L186: PRESIDENCIA EJECUTIVA DEL CONSEJO | M186: 40 | N186: DIRECCION GENERAL BANCO BASE | O186: 440 | P186: DIRECCION DE CONTRALORIA Y PREVENCION | Q186: 4430 | R186: DIRECCION DE OPERACIONES | S186: 44300 | T186: DIRECCION DE OPERACIONES | U186: 443000 | V186: DIRECCION DE OPERACIONES | W186: 100101 | X186: CORPORATIVO | Y186: 4 | Z186: CORPORATIVO | AA186: 1 | AB186: NEGOCIO EN MARCHA | AC186: 1 | AD186: BANCO | AE186: 1 | AF186: BACK | AG186: 100101 | AH186: CORPORATIVO | AI186: NGALLEGOS@BANCOBASE.COM | AJ186: 40330
A187: GVILLARREC | B187: 317 | C187: GERARDO ISRAEL VILLARREAL COSSIO | D187: 10077 | E187: SUBDIRECTOR DE CONCILIACIONES, EMISION Y SERVICIOS | F187: MONTERREY | G187: 618 | H187: NANCY GALLEGOS RUIZ | I187: 8387 | J187: DIRECTOR DE OPERACIONES | K187: 1 | L187: PRESIDENCIA EJECUTIVA DEL CONSEJO | M187: 40 | N187: DIRECCION GENERAL BANCO BASE | O187: 440 | P187: DIRECCION DE CONTRALORIA Y PREVENCION | Q187: 4430 | R187: DIRECCION DE OPERACIONES | S187: 44200 | T187: SUBDIRECCION CONCILIACIONES EMISION Y SERVICIOS | U187: 442000 | V187: SUBDIRECCION CONCILIACIONES EMISION Y SERVICIOS | W187: 100101 | X187: CORPORATIVO | Y187: 4 | Z187: CORPORATIVO | AA187: 1 | AB187: NEGOCIO EN MARCHA | AC187: 1 | AD187: BANCO | AE187: 1 | AF187: BACK | AG187: 100101 | AH187: CORPORATIVO | AI187: GVILLARR02@BANCOBASE.COM | AJ187: 38777
A188: PAGUILERA | B188: 782 | C188: ADRIANA PAMELA AGUILERA FLORES | D188: 9082 | E188: GERENTE BACKOFFICE DERIVADOS | F188: MONTERREY | G188: 317 | H188: GERARDO ISRAEL VILLARREAL COSSIO | I188: 10077 | J188: SUBDIRECTOR DE CONCILIACIONES, EMISION Y SERVICIOS | K188: 1 | L188: PRESIDENCIA EJECUTIVA DEL CONSEJO | M188: 40 | N188: DIRECCION GENERAL BANCO BASE | O188: 440 | P188: DIRECCION DE CONTRALORIA Y PREVENCION | Q188: 4430 | R188: DIRECCION DE OPERACIONES | S188: 44200 | T188: SUBDIRECCION CONCILIACIONES EMISION Y SERVICIOS | U188: 442000 | V188: SUBDIRECCION CONCILIACIONES EMISION Y SERVICIOS | W188: 100101 | X188: CORPORATIVO | Y188: 4 | Z188: CORPORATIVO | AA188: 1 | AB188: NEGOCIO EN MARCHA | AC188: 1 | AD188: BANCO | AE188: 1 | AF188: BACK | AG188: 100101 | AH188: CORPORATIVO | AI188: PAGUILERA@BANCOBASE.COM | AJ188: 40771
A189: EGONZALEZG | B189: 1603 | C189: ESCARLEET GONZALEZ GUTIERREZ | D189: 9117 | E189: ESPECIALISTA BACKOFFICE DERIVADOS | F189: MONTERREY | G189: 782 | H189: ADRIANA PAMELA AGUILERA FLORES | I189: 9082 | J189: GERENTE BACKOFFICE DERIVADOS | K189: 1 | L189: PRESIDENCIA EJECUTIVA DEL CONSEJO | M189: 40 | N189: DIRECCION GENERAL BANCO BASE | O189: 440 | P189: DIRECCION DE CONTRALORIA Y PREVENCION | Q189: 4430 | R189: DIRECCION DE OPERACIONES | S189: 44200 | T189: SUBDIRECCION CONCILIACIONES EMISION Y SERVICIOS | U189: 442000 | V189: SUBDIRECCION CONCILIACIONES EMISION Y SERVICIOS | W189: 100101 | X189: CORPORATIVO | Y189: 4 | Z189: CORPORATIVO | AA189: 1 | AB189: NEGOCIO EN MARCHA | AC189: 1 | AD189: BANCO | AE189: 1 | AF189: BACK | AG189: 100101 | AH189: CORPORATIVO | AI189: EGONZALEZG@BANCOBASE.COM | AJ189: 42583
A190: ASOTOG | B190: 3117 | C190: ADOLFO DE JESUS SOTO GARCIA | D190: 10260 | E190: ANALISTA DE BACKOFFICE | F190: MONTERREY | G190: 782 | H190: ADRIANA PAMELA AGUILERA FLORES | I190: 9082 | J190: GERENTE BACKOFFICE DERIVADOS | K190: 1 | L190: PRESIDENCIA EJECUTIVA DEL CONSEJO | M190: 40 | N190: DIRECCION GENERAL BANCO BASE | O190: 440 | P190: DIRECCION DE CONTRALORIA Y PREVENCION | Q190: 4430 | R190: DIRECCION DE OPERACIONES | S190: 44200 | T190: SUBDIRECCION CONCILIACIONES EMISION Y SERVICIOS | U190: 442000 | V190: SUBDIRECCION CONCILIACIONES EMISION Y SERVICIOS | W190: 100101 | X190: CORPORATIVO | Y190: 4 | Z190: CORPORATIVO | AA190: 1 | AB190: NEGOCIO EN MARCHA | AC190: 1 | AD190: BANCO | AE190: 1 | AF190: BACK | AG190: 100101 | AH190: CORPORATIVO | AI190: ASOTOG@BANCOBASE.COM | AJ190: 45428
A191: JMICHEL | B191: 3420 | C191: JUAN CARLOS MICHEL PRESAS | D191: 8686 | E191: ANALISTA DE BACKOFFICE | F191: MONTERREY | G191: 782 | H191: ADRIANA PAMELA AGUILERA FLORES | I191: 9082 | J191: GERENTE BACKOFFICE DERIVADOS | K191: 1 | L191: PRESIDENCIA EJECUTIVA DEL CONSEJO | M191: 40 | N191: DIRECCION GENERAL BANCO BASE | O191: 440 | P191: DIRECCION DE CONTRALORIA Y PREVENCION | Q191: 4430 | R191: DIRECCION DE OPERACIONES | S191: 44200 | T191: SUBDIRECCION CONCILIACIONES EMISION Y SERVICIOS | U191: 442000 | V191: SUBDIRECCION CONCILIACIONES EMISION Y SERVICIOS | W191: 100101 | X191: CORPORATIVO | Y191: 4 | Z191: CORPORATIVO | AA191: 1 | AB191: NEGOCIO EN MARCHA | AC191: 1 | AD191: BANCO | AE191: 1 | AF191: BACK | AG191: 100101 | AH191: CORPORATIVO | AI191: JMICHEL@BANCOBASE.COM | AJ191: 45778
A192: EORNELAS | B192: 1808 | C192: EDGAR ESAU ORNELAS PAREDES | D192: 10258 | E192: ESPECIALISTA BACKOFFICE BURSATIL | F192: MONTERREY | G192: 317 | H192: GERARDO ISRAEL VILLARREAL COSSIO | I192: 10077 | J192: SUBDIRECTOR DE CONCILIACIONES, EMISION Y SERVICIOS | K192: 1 | L192: PRESIDENCIA EJECUTIVA DEL CONSEJO | M192: 40 | N192: DIRECCION GENERAL BANCO BASE | O192: 440 | P192: DIRECCION DE CONTRALORIA Y PREVENCION | Q192: 4430 | R192: DIRECCION DE OPERACIONES | S192: 44500 | T192: SUBDIRECCION BACK CAPTACION Y BURSATIL | U192: 445000 | V192: SUBDIRECCION BACK CAPTACION Y BURSATIL | W192: 100101 | X192: CORPORATIVO | Y192: 4 | Z192: CORPORATIVO | AA192: 1 | AB192: NEGOCIO EN MARCHA | AC192: 1 | AD192: BANCO | AE192: 1 | AF192: BACK | AG192: 100101 | AH192: CORPORATIVO | AI192: EORNELAS@BANCOBASE.COM | AJ192: 42932
A193: GHERNANDEB | B193: 1339 | C193: GRETHA CONCEPCION HERNANDEZ BARBOSA | D193: 9125 | E193: ESPECIALISTA BACKOFFICE MD | F193: MONTERREY | G193: 317 | H193: GERARDO ISRAEL VILLARREAL COSSIO | I193: 10077 | J193: SUBDIRECTOR DE CONCILIACIONES, EMISION Y SERVICIOS | K193: 1 | L193: PRESIDENCIA EJECUTIVA DEL CONSEJO | M193: 40 | N193: DIRECCION GENERAL BANCO BASE | O193: 440 | P193: DIRECCION DE CONTRALORIA Y PREVENCION | Q193: 4430 | R193: DIRECCION DE OPERACIONES | S193: 44500 | T193: SUBDIRECCION BACK CAPTACION Y BURSATIL | U193: 445000 | V193: SUBDIRECCION BACK CAPTACION Y BURSATIL | W193: 100101 | X193: CORPORATIVO | Y193: 4 | Z193: CORPORATIVO | AA193: 1 | AB193: NEGOCIO EN MARCHA | AC193: 1 | AD193: BANCO | AE193: 1 | AF193: BACK | AG193: 100101 | AH193: CORPORATIVO | AI193: GHERNANDEB@BANCOBASE.COM | AJ193: 42201
A194: POTERO | B194: 3067 | C194: PEDRO DE JESUS OTERO MARTINEZ | D194: 10069 | E194: ANALISTA DE BACKOFFICE | F194: MONTERREY | G194: 317 | H194: GERARDO ISRAEL VILLARREAL COSSIO | I194: 10077 | J194: SUBDIRECTOR DE CONCILIACIONES, EMISION Y SERVICIOS | K194: 1 | L194: PRESIDENCIA EJECUTIVA DEL CONSEJO | M194: 40 | N194: DIRECCION GENERAL BANCO BASE | O194: 440 | P194: DIRECCION DE CONTRALORIA Y PREVENCION | Q194: 4430 | R194: DIRECCION DE OPERACIONES | S194: 44500 | T194: SUBDIRECCION BACK CAPTACION Y BURSATIL | U194: 445000 | V194: SUBDIRECCION BACK CAPTACION Y BURSATIL | W194: 100101 | X194: CORPORATIVO | Y194: 4 | Z194: CORPORATIVO | AA194: 1 | AB194: NEGOCIO EN MARCHA | AC194: 1 | AD194: BANCO | AE194: 1 | AF194: BACK | AG194: 100101 | AH194: CORPORATIVO | AI194: POTERO@BANCOBASE.COM | AJ194: 45383
A195: DQUINTERO | B195: 2623 | C195: DANIELA SOFIA QUINTERO LOPEZ | D195: 9786 | E195: COORDINADOR DE BACKOFICE PREVISION SOCIAL | F195: MONTERREY | G195: 317 | H195: GERARDO ISRAEL VILLARREAL COSSIO | I195: 10077 | J195: SUBDIRECTOR DE CONCILIACIONES, EMISION Y SERVICIOS | K195: 1 | L195: PRESIDENCIA EJECUTIVA DEL CONSEJO | M195: 40 | N195: DIRECCION GENERAL BANCO BASE | O195: 440 | P195: DIRECCION DE CONTRALORIA Y PREVENCION | Q195: 4430 | R195: DIRECCION DE OPERACIONES | S195: 44500 | T195: SUBDIRECCION BACK CAPTACION Y BURSATIL | U195: 445000 | V195: SUBDIRECCION BACK CAPTACION Y BURSATIL | W195: 100101 | X195: CORPORATIVO | Y195: 4 | Z195: CORPORATIVO | AA195: 1 | AB195: NEGOCIO EN MARCHA | AC195: 1 | AD195: BANCO | AE195: 1 | AF195: BACK | AG195: 100101 | AH195: CORPORATIVO | AI195: DQUINTERO@BANCOBASE.COM | AJ195: 44621
... A218: DTREVINO | B218: 1244 | C218: DIANA ALEJANDRA TREVIÑO GONGORA | D218: 10000 | E218: SUBDIRECTOR DE MEDIOS DE PAGO | F218: MONTERREY | G218: 618 | H218: NANCY GALLEGOS RUIZ | I218: 8387 | J218: DIRECTOR DE OPERACIONES | K218: 1 | L218: PRESIDENCIA EJECUTIVA DEL CONSEJO | M218: 40 | N218: DIRECCION GENERAL BANCO BASE | O218: 440 | P218: DIRECCION DE CONTRALORIA Y PREVENCION | Q218: 4430 | R218: DIRECCION DE OPERACIONES | S218: 44350 | T218: MEDIOS DE PAGO | U218: 443500 | V218: MEDIOS DE PAGO | W218: 100101 | X218: CORPORATIVO | Y218: 4 | Z218: CORPORATIVO | AA218: 1 | AB218: NEGOCIO EN MARCHA | AC218: 1 | AD218: BANCO | AE218: 1 | AF218: BACK | AG218: 100101 | AH218: CORPORATIVO | AI218: DTREVINO@BANCOBASE.COM | AJ218: 41990
A219: HMARTINEZS | B219: 2564 | C219: HECTOR NOE MARTINEZ SALDAÑA | D219: 5056 | E219: ESPECIALISTA DE LIQUIDACIONES | F219: MONTERREY | I219: 8388 | J219: GERENTE DE CONFIRMACIONES Y LIQUIDACIONES | K219: 1 | L219: PRESIDENCIA EJECUTIVA DEL CONSEJO | M219: 40 | N219: DIRECCION GENERAL BANCO BASE | O219: 440 | P219: DIRECCION DE CONTRALORIA Y PREVENCION | Q219: 4430 | R219: DIRECCION DE OPERACIONES | S219: 44350 | T219: MEDIOS DE PAGO | U219: 443510 | V219: CONFIRMACIONES Y LIQUIDACIONES | W219: 100101 | X219: CORPORATIVO | Y219: 4 | Z219: CORPORATIVO | AA219: 1 | AB219: NEGOCIO EN MARCHA | AC219: 1 | AD219: BANCO | AE219: 1 | AF219: BACK | AG219: 100101 | AH219: CORPORATIVO | AI219: HMARTINEZS@BANCOBASE.COM | AJ219: 44485
A220: SPRADO | B220: 1888 | C220: SERGIO ALBERTO PRADO RODRIGUEZ | D220: 8700 | E220: ANALISTA DE CONFIRMACIONES Y LIQUIDACIONES | F220: MONTERREY | G220: 1244 | H220: DIANA ALEJANDRA TREVIÑO GONGORA | I220: 10000 | J220: SUBDIRECTOR DE MEDIOS DE PAGO | K220: 1 | L220: PRESIDENCIA EJECUTIVA DEL CONSEJO | M220: 40 | N220: DIRECCION GENERAL BANCO BASE | O220: 440 | P220: DIRECCION DE CONTRALORIA Y PREVENCION | Q220: 4430 | R220: DIRECCION DE OPERACIONES | S220: 44350 | T220: MEDIOS DE PAGO | U220: 443510 | V220: CONFIRMACIONES Y LIQUIDACIONES | W220: 100101 | X220: CORPORATIVO | Y220: 4 | Z220: CORPORATIVO | AA220: 1 | AB220: NEGOCIO EN MARCHA | AC220: 1 | AD220: BANCO | AE220: 1 | AF220: BACK | AG220: 100101 | AH220: CORPORATIVO | AI220: SPRADO@BANCOBASE.COM | AJ220: 43055
A221: NPEREZ | B221: 2678 | C221: NALLELY SARAHI PEREZ RAMIREZ | D221: 8142 | E221: ANALISTA DE LIQUIDACIONES | F221: MONTERREY | I221: 8388 | J221: GERENTE DE CONFIRMACIONES Y LIQUIDACIONES | K221: 1 | L221: PRESIDENCIA EJECUTIVA DEL CONSEJO | M221: 40 | N221: DIRECCION GENERAL BANCO BASE | O221: 440 | P221: DIRECCION DE CONTRALORIA Y PREVENCION | Q221: 4430 | R221: DIRECCION DE OPERACIONES | S221: 44350 | T221: MEDIOS DE PAGO | U221: 443510 | V221: CONFIRMACIONES Y LIQUIDACIONES | W221: 100101 | X221: CORPORATIVO | Y221: 4 | Z221: CORPORATIVO | AA221: 1 | AB221: NEGOCIO EN MARCHA | AC221: 1 | AD221: BANCO | AE221: 1 | AF221: BACK | AG221: 100101 | AH221: CORPORATIVO | AI221: NPEREZ@BANCOBASE.COM | AJ221: 44728
A222: JFLORESG | B222: 1204 | C222: JONATHAN EDGAR FLORES GONZALEZ | D222: 9084 | E222: ANALISTA DE LIQUIDACIONES | F222: MONTERREY | I222: 8388 | J222: GERENTE DE CONFIRMACIONES Y LIQUIDACIONES | K222: 1 | L222: PRESIDENCIA EJECUTIVA DEL CONSEJO | M222: 40 | N222: DIRECCION GENERAL BANCO BASE | O222: 440 | P222: DIRECCION DE CONTRALORIA Y PREVENCION | Q222: 4430 | R222: DIRECCION DE OPERACIONES | S222: 44350 | T222: MEDIOS DE PAGO | U222: 443510 | V222: CONFIRMACIONES Y LIQUIDACIONES | W222: 100101 | X222: CORPORATIVO | Y222: 4 | Z222: CORPORATIVO | AA222: 1 | AB222: NEGOCIO EN MARCHA | AC222: 1 | AD222: BANCO | AE222: 1 | AF222: BACK | AG222: 100101 | AH222: CORPORATIVO | AI222: JFLORESG@BANCOBASE.COM | AJ222: 41913
A223: JAGUILARI | B223: 2643 | C223: JOSE ANTONIO AGUILAR IRACHETA | D223: 9085 | E223: ANALISTA DE LIQUIDACIONES | F223: MONTERREY | I223: 8388 | J223: GERENTE DE CONFIRMACIONES Y LIQUIDACIONES | K223: 1 | L223: PRESIDENCIA EJECUTIVA DEL CONSEJO | M223: 40 | N223: DIRECCION GENERAL BANCO BASE | O223: 440 | P223: DIRECCION DE CONTRALORIA Y PREVENCION | Q223: 4430 | R223: DIRECCION DE OPERACIONES | S223: 44350 | T223: MEDIOS DE PAGO | U223: 443510 | V223: CONFIRMACIONES Y LIQUIDACIONES | W223: 100101 | X223: CORPORATIVO | Y223: 4 | Z223: CORPORATIVO | AA223: 1 | AB223: NEGOCIO EN MARCHA | AC223: 1 | AD223: BANCO | AE223: 1 | AF223: BACK | AG223: 100101 | AH223: CORPORATIVO | AI223: JAGUILARI@BANCOBASE.COM | AJ223: 44682
A224: KIBARRA | B224: 3456 | C224: KASSANDRA XIOMARA IBARRA LARA | D224: 9043 | E224: ANALISTA DE LIQUIDACIONES | F224: MONTERREY | I224: 8388 | J224: GERENTE DE CONFIRMACIONES Y LIQUIDACIONES | K224: 1 | L224: PRESIDENCIA EJECUTIVA DEL CONSEJO | M224: 40 | N224: DIRECCION GENERAL BANCO BASE | O224: 440 | P224: DIRECCION DE CONTRALORIA Y PREVENCION | Q224: 4430 | R224: DIRECCION DE OPERACIONES | S224: 44350 | T224: MEDIOS DE PAGO | U224: 443510 | V224: CONFIRMACIONES Y LIQUIDACIONES | W224: 100101 | X224: CORPORATIVO | Y224: 4 | Z224: CORPORATIVO | AA224: 1 | AB224: NEGOCIO EN MARCHA | AC224: 1 | AD224: BANCO | AE224: 1 | AF224: BACK | AG224: 100101 | AH224: CORPORATIVO | AI224: KIBARRA@BANCOBASE.COM | AJ224: 45824
A225: JJALOMO | B225: 3681 | C225: JAVIER JALOMO ALANIS | D225: 9101 | E225: ANALISTA DE CONFIRMACIONES | F225: MONTERREY | I225: 8388 | J225: GERENTE DE CONFIRMACIONES Y LIQUIDACIONES | K225: 1 | L225: PRESIDENCIA EJECUTIVA DEL CONSEJO | M225: 40 | N225: DIRECCION GENERAL BANCO BASE | O225: 440 | P225: DIRECCION DE CONTRALORIA Y PREVENCION | Q225: 4430 | R225: DIRECCION DE OPERACIONES | S225: 44350 | T225: MEDIOS DE PAGO | U225: 443510 | V225: CONFIRMACIONES Y LIQUIDACIONES | W225: 100101 | X225: CORPORATIVO | Y225: 4 | Z225: CORPORATIVO | AA225: 1 | AB225: NEGOCIO EN MARCHA | AC225: 1 | AD225: BANCO | AE225: 1 | AF225: BACK | AG225: 100101 | AH225: CORPORATIVO | AI225: JJALOMO@BANCOBASE.COM | AJ225: 45979
A226: DRAMIREZO | B226: 3023 | C226: DEVANNY ARLETTE RAMIREZ OLVERA | D226: 9089 | E226: ANALISTA DE LIQUIDACIONES | F226: MONTERREY | I226: 8388 | J226: GERENTE DE CONFIRMACIONES Y LIQUIDACIONES | K226: 1 | L226: PRESIDENCIA EJECUTIVA DEL CONSEJO | M226: 40 | N226: DIRECCION GENERAL BANCO BASE | O226: 440 | P226: DIRECCION DE CONTRALORIA Y PREVENCION | Q226: 4430 | R226: DIRECCION DE OPERACIONES | S226: 44350 | T226: MEDIOS DE PAGO | U226: 443510 | V226: CONFIRMACIONES Y LIQUIDACIONES | W226: 100101 | X226: CORPORATIVO | Y226: 4 | Z226: CORPORATIVO | AA226: 1 | AB226: NEGOCIO EN MARCHA | AC226: 1 | AD226: BANCO | AE226: 1 | AF226: BACK | AG226: 100101 | AH226: CORPORATIVO | AI226: DRAMIREZO@BANCOBASE.COM | AJ226: 45323
A227: AARANDA | B227: 3910 | C227: ANGEL ISAI ARANDA AGUILAR | D227: 10313 | E227: ANALISTA DE CONFIRMACIONES | F227: MONTERREY | I227: 8388 | J227: GERENTE DE CONFIRMACIONES Y LIQUIDACIONES | K227: 1 | L227: PRESIDENCIA EJECUTIVA DEL CONSEJO | M227: 40 | N227: DIRECCION GENERAL BANCO BASE | O227: 440 | P227: DIRECCION DE CONTRALORIA Y PREVENCION | Q227: 4430 | R227: DIRECCION DE OPERACIONES | S227: 44350 | T227: MEDIOS DE PAGO | U227: 443510 | V227: CONFIRMACIONES Y LIQUIDACIONES | W227: 100101 | X227: CORPORATIVO | Y227: 4 | Z227: CORPORATIVO | AA227: 1 | AB227: NEGOCIO EN MARCHA | AC227: 1 | AD227: BANCO | AE227: 1 | AF227: BACK | AG227: 100101 | AH227: CORPORATIVO | AI227: AARANDA@BANCOBASE.COM | AJ227: 46189
A228: DMARTINEG | B228: 3471 | C228: DEBANY MICHEL MARTINEZ GUAJARDO | D228: 9126 | E228: ANALISTA DE LIQUIDACIONES | F228: MONTERREY | I228: 8388 | J228: GERENTE DE CONFIRMACIONES Y LIQUIDACIONES | K228: 1 | L228: PRESIDENCIA EJECUTIVA DEL CONSEJO | M228: 40 | N228: DIRECCION GENERAL BANCO BASE | O228: 440 | P228: DIRECCION DE CONTRALORIA Y PREVENCION | Q228: 4430 | R228: DIRECCION DE OPERACIONES | S228: 44350 | T228: MEDIOS DE PAGO | U228: 443510 | V228: CONFIRMACIONES Y LIQUIDACIONES | W228: 100101 | X228: CORPORATIVO | Y228: 4 | Z228: CORPORATIVO | AA228: 1 | AB228: NEGOCIO EN MARCHA | AC228: 1 | AD228: BANCO | AE228: 1 | AF228: BACK | AG228: 100101 | AH228: CORPORATIVO | AI228: DMARTINEG@BANCOBASE.COM | AJ228: 45839
A229: FCORTINA | B229: 1298 | C229: FERNANDO CORTINA GARZA | D229: 8244 | E229: GERENTE DE CORRESPONSALIAS Y CUSTOMER SERVICES | F229: MONTERREY | G229: 1244 | H229: DIANA ALEJANDRA TREVIÑO GONGORA | I229: 10000 | J229: SUBDIRECTOR DE MEDIOS DE PAGO | K229: 1 | L229: PRESIDENCIA EJECUTIVA DEL CONSEJO | M229: 40 | N229: DIRECCION GENERAL BANCO BASE | O229: 440 | P229: DIRECCION DE CONTRALORIA Y PREVENCION | Q229: 4430 | R229: DIRECCION DE OPERACIONES | S229: 44350 | T229: MEDIOS DE PAGO | U229: 443300 | V229: GERENCIA CONTACT CENTER | W229: 100101 | X229: CORPORATIVO | Y229: 4 | Z229: CORPORATIVO | AA229: 1 | AB229: NEGOCIO EN MARCHA | AC229: 1 | AD229: BANCO | AE229: 1 | AF229: BACK | AG229: 100101 | AH229: CORPORATIVO | AI229: FCORTINA@BANCOBASE.COM | AJ229: 42125
A230: KZAMARRON | B230: 760 | C230: KARLA MAGALY ZAMARRON TREVIÑO | D230: 9078 | E230: COORDINADOR ACLARACION Y SERVICIO | F230: MONTERREY | G230: 1298 | H230: FERNANDO CORTINA GARZA | I230: 8244 | J230: GERENTE DE CORRESPONSALIAS Y CUSTOMER SERVICES | K230: 1 | L230: PRESIDENCIA EJECUTIVA DEL CONSEJO | M230: 40 | N230: DIRECCION GENERAL BANCO BASE | O230: 440 | P230: DIRECCION DE CONTRALORIA Y PREVENCION | Q230: 4430 | R230: DIRECCION DE OPERACIONES | S230: 44350 | T230: MEDIOS DE PAGO | U230: 443300 | V230: GERENCIA CONTACT CENTER | W230: 100101 | X230: CORPORATIVO | Y230: 4 | Z230: CORPORATIVO | AA230: 1 | AB230: NEGOCIO EN MARCHA | AC230: 1 | AD230: BANCO | AE230: 1 | AF230: BACK | AG230: 100101 | AH230: CORPORATIVO | AI230: KZAMARRON@BANCOBASE.COM | AJ230: 40728
A231: ACAMARILLO | B231: 3395 | C231: ANTONIO SEBASTIAN CAMARILLO SALINAS | D231: 9113 | E231: EJECUTIVO ACLARACION Y SERVICIO | F231: MONTERREY | G231: 760 | H231: KARLA MAGALY ZAMARRON TREVIÑO | I231: 9078 | J231: COORDINADOR ACLARACION Y SERVICIO | K231: 1 | L231: PRESIDENCIA EJECUTIVA DEL CONSEJO | M231: 40 | N231: DIRECCION GENERAL BANCO BASE | O231: 440 | P231: DIRECCION DE CONTRALORIA Y PREVENCION | Q231: 4430 | R231: DIRECCION DE OPERACIONES | S231: 44350 | T231: MEDIOS DE PAGO | U231: 443300 | V231: GERENCIA CONTACT CENTER | W231: 100101 | X231: CORPORATIVO | Y231: 4 | Z231: CORPORATIVO | AA231: 1 | AB231: NEGOCIO EN MARCHA | AC231: 1 | AD231: BANCO | AE231: 1 | AF231: BACK | AG231: 100101 | AH231: CORPORATIVO | AI231: ACAMARILLO@BANCOBASE.COM | AJ231: 45768
A232: YRODRIGUEZ | B232: 3307 | C232: YERALDIN LIZETH RODRIGUEZ AGUILAR | D232: 9121 | E232: EJECUTIVO ACLARACION Y SERVICIO | F232: MONTERREY | G232: 760 | H232: KARLA MAGALY ZAMARRON TREVIÑO | I232: 9078 | J232: COORDINADOR ACLARACION Y SERVICIO | K232: 1 | L232: PRESIDENCIA EJECUTIVA DEL CONSEJO | M232: 40 | N232: DIRECCION GENERAL BANCO BASE | O232: 440 | P232: DIRECCION DE CONTRALORIA Y PREVENCION | Q232: 4430 | R232: DIRECCION DE OPERACIONES | S232: 44350 | T232: MEDIOS DE PAGO | U232: 443300 | V232: GERENCIA CONTACT CENTER | W232: 100101 | X232: CORPORATIVO | Y232: 4 | Z232: CORPORATIVO | AA232: 1 | AB232: NEGOCIO EN MARCHA | AC232: 1 | AD232: BANCO | AE232: 1 | AF232: BACK | AG232: 100101 | AH232: CORPORATIVO | AI232: YRODRIGUEZ@BANCOBASE.COM | AJ232: 45663
A233: SFLORESG | B233: 3442 | C233: SAMANTHA PAULINA FLORES GARCIA | D233: 8693 | E233: EJECUTIVO ACLARACION Y SERVICIO | F233: MONTERREY | G233: 760 | H233: KARLA MAGALY ZAMARRON TREVIÑO | I233: 9078 | J233: COORDINADOR ACLARACION Y SERVICIO | K233: 1 | L233: PRESIDENCIA EJECUTIVA DEL CONSEJO | M233: 40 | N233: DIRECCION GENERAL BANCO BASE | O233: 440 | P233: DIRECCION DE CONTRALORIA Y PREVENCION | Q233: 4430 | R233: DIRECCION DE OPERACIONES | S233: 44350 | T233: MEDIOS DE PAGO | U233: 443300 | V233: GERENCIA CONTACT CENTER | W233: 100101 | X233: CORPORATIVO | Y233: 4 | Z233: CORPORATIVO | AA233: 1 | AB233: NEGOCIO EN MARCHA | AC233: 1 | AD233: BANCO | AE233: 1 | AF233: BACK | AG233: 100101 | AH233: CORPORATIVO | AI233: SFLORESG@BANCOBASE.COM | AJ233: 45810
A234: MTREVINON | B234: 3571 | C234: MELISSA TREVINO NEGRETE | D234: 9127 | E234: EJECUTIVO ACLARACION Y SERVICIO | F234: MONTERREY | G234: 760 | H234: KARLA MAGALY ZAMARRON TREVIÑO | I234: 9078 | J234: COORDINADOR ACLARACION Y SERVICIO | K234: 1 | L234: PRESIDENCIA EJECUTIVA DEL CONSEJO | M234: 40 | N234: DIRECCION GENERAL BANCO BASE | O234: 440 | P234: DIRECCION DE CONTRALORIA Y PREVENCION | Q234: 4430 | R234: DIRECCION DE OPERACIONES | S234: 44350 | T234: MEDIOS DE PAGO | U234: 443300 | V234: GERENCIA CONTACT CENTER | W234: 100101 | X234: CORPORATIVO | Y234: 4 | Z234: CORPORATIVO | AA234: 6 | AB234: PROYECTO REGULATORIOS | AC234: 1 | AD234: BANCO | AE234: 1 | AF234: BACK | AG234: 100101 | AH234: CORPORATIVO | AI234: MTREVINON@BANCOBASE.COM | AJ234: 45917
A235: ILARA | B235: 3680 | C235: ILEANA MICHELLE LARA ALDABA | D235: 8714 | E235: EJECUTIVO ACLARACION Y SERVICIO | F235: MONTERREY | G235: 760 | H235: KARLA MAGALY ZAMARRON TREVIÑO | I235: 9078 | J235: COORDINADOR ACLARACION Y SERVICIO | K235: 1 | L235: PRESIDENCIA EJECUTIVA DEL CONSEJO | M235: 40 | N235: DIRECCION GENERAL BANCO BASE | O235: 440 | P235: DIRECCION DE CONTRALORIA Y PREVENCION | Q235: 4430 | R235: DIRECCION DE OPERACIONES | S235: 44350 | T235: MEDIOS DE PAGO | U235: 443300 | V235: GERENCIA CONTACT CENTER | W235: 100101 | X235: CORPORATIVO | Y235: 4 | Z235: CORPORATIVO | AA235: 6 | AB235: PROYECTO REGULATORIOS | AC235: 1 | AD235: BANCO | AE235: 1 | AF235: BACK | AG235: 100101 | AH235: CORPORATIVO | AI235: ILARA@BANCOBASE.COM | AJ235: 45979
A236: YRUIZD | B236: 3721 | C236: YAZMIN RUIZ DE LEON | D236: 8715 | E236: EJECUTIVO ACLARACION Y SERVICIO | F236: MONTERREY | G236: 760 | H236: KARLA MAGALY ZAMARRON TREVIÑO | I236: 9078 | J236: COORDINADOR ACLARACION Y SERVICIO | K236: 1 | L236: PRESIDENCIA EJECUTIVA DEL CONSEJO | M236: 40 | N236: DIRECCION GENERAL BANCO BASE | O236: 440 | P236: DIRECCION DE CONTRALORIA Y PREVENCION | Q236: 4430 | R236: DIRECCION DE OPERACIONES | S236: 44350 | T236: MEDIOS DE PAGO | U236: 443300 | V236: GERENCIA CONTACT CENTER | W236: 100101 | X236: CORPORATIVO | Y236: 4 | Z236: CORPORATIVO | AA236: 6 | AB236: PROYECTO REGULATORIOS | AC236: 1 | AD236: BANCO | AE236: 1 | AF236: BACK | AG236: 100101 | AH236: CORPORATIVO | AI236: YRUIZD@BANCOBASE.COM | AJ236: 46027
A237: PPOSADAS | B237: 3748 | C237: PABLO POSADAS CRUZ | D237: 10159 | E237: EJECUTIVO ACLARACION Y SERVICIO | F237: MONTERREY | G237: 760 | H237: KARLA MAGALY ZAMARRON TREVIÑO | I237: 9078 | J237: COORDINADOR ACLARACION Y SERVICIO | K237: 1 | L237: PRESIDENCIA EJECUTIVA DEL CONSEJO | M237: 40 | N237: DIRECCION GENERAL BANCO BASE | O237: 440 | P237: DIRECCION DE CONTRALORIA Y PREVENCION | Q237: 4430 | R237: DIRECCION DE OPERACIONES | S237: 44350 | T237: MEDIOS DE PAGO | U237: 443300 | V237: GERENCIA CONTACT CENTER | W237: 100101 | X237: CORPORATIVO | Y237: 4 | Z237: CORPORATIVO | AA237: 1 | AB237: NEGOCIO EN MARCHA | AC237: 1 | AD237: BANCO | AE237: 1 | AF237: BACK | AG237: 100101 | AH237: CORPORATIVO | AI237: PPOSADAS@BANCOBASE.COM | AJ237: 46056
A238: ZGARZA | B238: 3751 | C238: ZAIDA LETICIA GARZA DOMINGUEZ | D238: 10218 | E238: EJECUTIVO ACLARACION Y SERVICIO | F238: MONTERREY | G238: 760 | H238: KARLA MAGALY ZAMARRON TREVIÑO | I238: 9078 | J238: COORDINADOR ACLARACION Y SERVICIO | K238: 1 | L238: PRESIDENCIA EJECUTIVA DEL CONSEJO | M238: 40 | N238: DIRECCION GENERAL BANCO BASE | O238: 440 | P238: DIRECCION DE CONTRALORIA Y PREVENCION | Q238: 4430 | R238: DIRECCION DE OPERACIONES | S238: 44350 | T238: MEDIOS DE PAGO | U238: 443300 | V238: GERENCIA CONTACT CENTER | W238: 100101 | X238: CORPORATIVO | Y238: 4 | Z238: CORPORATIVO | AA238: 1 | AB238: NEGOCIO EN MARCHA | AC238: 1 | AD238: BANCO | AE238: 1 | AF238: BACK | AG238: 100101 | AH238: CORPORATIVO | AI238: ZGARZA@BANCOBASE.COM | AJ238: 46056
A239: SSALAZARA | B239: 3782 | C239: STEPHANIE SALAZAR ARAUJO | D239: 8143 | E239: EJECUTIVO ACLARACION Y SERVICIO | F239: MONTERREY | G239: 760 | H239: KARLA MAGALY ZAMARRON TREVIÑO | I239: 9078 | J239: COORDINADOR ACLARACION Y SERVICIO | K239: 1 | L239: PRESIDENCIA EJECUTIVA DEL CONSEJO | M239: 40 | N239: DIRECCION GENERAL BANCO BASE | O239: 440 | P239: DIRECCION DE CONTRALORIA Y PREVENCION | Q239: 4430 | R239: DIRECCION DE OPERACIONES | S239: 44350 | T239: MEDIOS DE PAGO | U239: 443300 | V239: GERENCIA CONTACT CENTER | W239: 100101 | X239: CORPORATIVO | Y239: 4 | Z239: CORPORATIVO | AA239: 1 | AB239: NEGOCIO EN MARCHA | AC239: 1 | AD239: BANCO | AE239: 1 | AF239: BACK | AG239: 100101 | AH239: CORPORATIVO | AI239: SSALAZARA@BANCOBASE.COM | AJ239: 46098
A240: VCRUZ | B240: 3393 | C240: VALERIA ELIZABETH CRUZ LIRA | D240: 9114 | E240: ANALISTA DE CALIDAD Y SERVICIO | F240: MONTERREY | G240: 760 | H240: KARLA MAGALY ZAMARRON TREVIÑO | I240: 9078 | J240: COORDINADOR ACLARACION Y SERVICIO | K240: 1 | L240: PRESIDENCIA EJECUTIVA DEL CONSEJO | M240: 40 | N240: DIRECCION GENERAL BANCO BASE | O240: 440 | P240: DIRECCION DE CONTRALORIA Y PREVENCION | Q240: 4430 | R240: DIRECCION DE OPERACIONES | S240: 44350 | T240: MEDIOS DE PAGO | U240: 443300 | V240: GERENCIA CONTACT CENTER | W240: 100101 | X240: CORPORATIVO | Y240: 4 | Z240: CORPORATIVO | AA240: 1 | AB240: NEGOCIO EN MARCHA | AC240: 1 | AD240: BANCO | AE240: 1 | AF240: BACK | AG240: 100101 | AH240: CORPORATIVO | AI240: VCRUZ@BANCOBASE.COM | AJ240: 45768
... A286: JREGALADO | B286: 2940 | C286: JESSICA CAROLINA REGALADO BERLANGA | D286: 8725 | E286: GERENTE DE VALIDACION DE DOCUMENTOS | F286: MONTERREY | G286: 284 | H286: MERCED MAGDALENA BAEZ SALAZAR | I286: 8236 | J286: SUBDIRECTOR DE CONTROL DE DATOS | K286: 1 | L286: PRESIDENCIA EJECUTIVA DEL CONSEJO | M286: 40 | N286: DIRECCION GENERAL BANCO BASE | O286: 440 | P286: DIRECCION DE CONTRALORIA Y PREVENCION | Q286: 4460 | R286: DIRECCION DE CONTRALORIA | S286: 44610 | T286: SUBDIRECCION DE CONTROL DE DATOS | U286: 413111 | V286: SUBDIRECCION DE CONTROL DE DATOS | W286: 100101 | X286: CORPORATIVO | Y286: 4 | Z286: CORPORATIVO | AA286: 1 | AB286: NEGOCIO EN MARCHA | AC286: 1 | AD286: BANCO | AE286: 1 | AF286: BACK | AG286: 100101 | AH286: CORPORATIVO | AI286: JREGALADO@BANCOBASE.COM | AJ286: 45170
...
